Workbook

Sheet Exercise Master
A1: ADVENTURE RACING — EXERCISE MASTER DATABASE
A2: Exercise ID | B2: Exercise Name | C2: Exercise Type | D2: Movement Pattern | E2: Primary Muscles | F2: Secondary Muscles | G2: Equipment | H2: Novelty | I2: Injury Flags / Points of Failure | J2: Notes / Coaching Cues | K2: Equipment Substitutes | L2: Physical Proxy Exercises | M2: Contraindicated Body Parts | N2: Progression Exercise | O2: Regression Exercise | P2: Sport Count
A3: EX001 | B3: Back Squat (Barbell) | C3: Strength | D3: Squat | E3: Quadriceps, Glutes | F3: Hamstrings, Erector Spinae, Core | G3: Barbell, Squat rack | H3: Common | I3: Knee — valgus collapse; Lumbar — flexion under load; Shoulder/Wrist — bar rack mobility | J3: Brace before descent; knees track toes; chest up; foundational lower-body load | K3: Safety Bar Squat; Hack Squat machine; Smith Machine Squat; 🏠 Backpack loaded with books or water (goblet hold) for hotel squat | L3: EX002 — Goblet Squat (DB/KB); EX037 — Wall Sit | M3: Knee, Lumbar, Shoulder/Wrist | O3: EX002 — Goblet Squat (DB/KB) | P3: =COUNTIF('Sport-Exercise Map'!A:A,A3)
A4: EX002 | B4: Goblet Squat (DB/KB) | C4: Strength | D4: Squat | E4: Quadriceps, Glutes | F4: Core, Upper Back | G4: Dumbbell, Kettlebell | H4: Common | I4: Knee — valgus at depth; Wrist — grip discomfort under fatigue | J4: Counterbalance keeps torso upright; best hotel substitute for back squat | K4: Bodyweight squat (no load); Sandbag Goblet Squat; 🏠 Gallon water jug (~8.5 lb) as light goblet load; filled suitcase held at chest | L4: EX037 — Wall Sit; EX022 — Reverse Lunge (DB or BW) | M4: Knee, Wrist | N4: EX001 — Back Squat (Barbell) | P4: =COUNTIF('Sport-Exercise Map'!A:A,A4)
A5: EX003 | B5: Romanian Deadlift (Barbell) | C5: Strength | D5: Hinge | E5: Hamstrings, Glutes | F5: Erector Spinae, Forearms | G5: Barbell | H5: Common | I5: Lumbar — rounding under load; Hamstring — overstretching if flexibility limited | J5: Neutral spine; hinge at hip not waist; bar stays close to legs | K5: DB Romanian Deadlift; KB Deadlift; Trap Bar Deadlift; 🏠 Filled suitcase as barbell substitute (held at mid-thigh); backpack deadlift | L5: EX004 — Single-Leg RDL (DB); EX031 — Kettlebell Swing (Two-Hand) | M5: Lumbar, Hamstring | N5: EX020 — Nordic Hamstring Curl | P5: =COUNTIF('Sport-Exercise Map'!A:A,A5)
A6: EX004 | B6: Single-Leg RDL (DB) | C6: Strength | D6: Hinge, Single-Leg | E6: Glutes, Hamstrings | F6: Core, Hip Stabilisers | G6: Dumbbell | H6: Common | I6: Ankle — instability; Lumbar — rotation under fatigue; Hip — drop on standing side | J6: Slow eccentric critical for trail stability transfer; plant foot softly bent | K6: KB Single-Leg RDL; Single-Leg Good Morning (bodyweight); 🏠 Gallon water jug as light DB; bodyweight single-leg RDL (balance focus) | L6: EX039 — Glute Bridge (Double-Leg); EX019 — Barbell Hip Thrust | M6: Ankle, Lumbar, Hip | N6: EX117 — Loaded Step-Down (Eccentric Box) | P6: =COUNTIF('Sport-Exercise Map'!A:A,A6)
A7: EX005 | B7: Dead Hang | C7: Isometric | D7: Pull-V | E7: Grip, Forearms, Lats | F7: Shoulder Girdle, Core | G7: Pull-Up Bar, Hangboard | H7: Common | I7: Shoulder — impingement if passive hang without engagement; Wrist — extension load | J7: Actively pack shoulders; builds grip endurance for climbing and paddle holds | K7: Door frame hang; Towel-over-bar hang; Gymnastics rings; 🏠 Sturdy door frame; playground monkey bars; tree branch (test before full weight); stairwell railing overhang | L7: EX084 — Scapular Depression Hold; EX106 — Lock-Off Hold | M7: Shoulder, Wrist | N7: EX100 — Hangboard Half-Crimp Hold | O7: EX084 — Scapular Depression Hold | P7: =COUNTIF('Sport-Exercise Map'!A:A,A7)
A8: EX006 | B8: Pull-Up (BW) | C8: Strength | D8: Pull-V | E8: Latissimus Dorsi, Biceps | F8: Rear Delts, Core, Forearms | G8: Pull-Up Bar | H8: Common | I8: Shoulder — anterior capsule stress with excessive forward lean; Elbow — medial stress (wide grip) | J8: Full ROM; 3s eccentric for climbing carryover; supinated grip = chin-up | K8: Band-assisted Pull-Up; TRX Row (horizontal sub); Ring Row; 🏠 Playground bar or sturdy tree branch; parking garage beam (concrete); hotel room door-mount pull-up bar | L8: EX080 — Lat Pulldown (Wide Grip); EX078 — Single-Arm DB Row | M8: Shoulder, Elbow | N8: EX106 — Lock-Off Hold (90°, 120°) | O8: EX005 — Dead Hang | P8: =COUNTIF('Sport-Exercise Map'!A:A,A8)
A9: EX007 | B9: Box Jump | C9: Plyometric | D9: Squat, Hip-Ext | E9: Glutes, Quadriceps, Calves | F9: Hamstrings, Core | G9: Plyo box | H9: Common | I9: Ankle — landing mechanics; Knee — valgus on landing; Achilles — reactive load | J9: Land soft with hip hinge; step down, never jump down | K9: Step-up box jump (lower box); Stair jump; 🏠 Stair step or park bench for lower box jump; hotel bed (careful — test stability first) | L9: EX032 — Jump Squat (BW or Light Load); EX008 — Broad Jump | M9: Ankle, Knee, Achilles | N9: EX033 — Depth Drop (Eccentric Landing Practice) | O9: EX032 — Jump Squat (BW or Light Load) | P9: =COUNTIF('Sport-Exercise Map'!A:A,A9)
A10: EX008 | B10: Broad Jump | C10: Plyometric | D10: Hip-Ext, Locomotion | E10: Glutes, Hamstrings, Calves | F10: Core, Quads | H10: Common | I10: Ankle — landing impact; Knee — hyperextension on stick landing | J10: Max horizontal power; stick each landing; useful as field test metric | K10: Marked floor for distance; Sand or grass for impact reduction; 🏠 No equipment needed; mark distance with tape, shoes, or chalk | L10: EX007 — Box Jump; EX034 — Lateral Bound | M10: Ankle, Knee | N10: EX007 — Box Jump | O10: EX035 — Ankle Hops / Pogo Jumps | P10: =COUNTIF('Sport-Exercise Map'!A:A,A10)
A11: EX009 | B11: Farmer Carry | C11: Loaded Carry | D11: Carry | E11: Grip, Forearms, Trapezius | F11: Core, Glutes, Calves | G11: Dumbbell, Kettlebell, Barbell | H11: Common | I11: Lumbar — lateral flexion with asymmetric load; Shoulder — trap overload heavy loads | J11: Pack-carry sim; shoulders packed; tall gait; suitcase carry for unilateral demand | K11: Suitcase carry (one DB); Loaded backpack carry; Sandbag carry; 🏠 Gallon jugs in each hand; filled grocery bags; suitcases | L11: EX010 — Rucking (Weighted Hike); EX095 — Portage Carry Simulation | M11: Lumbar, Shoulder | N11: EX010 — Rucking (Weighted Hike) | P11: =COUNTIF('Sport-Exercise Map'!A:A,A11)
A12: EX010 | B12: Rucking (Weighted Hike) | C12: Loaded Carry | D12: Locomotion, Carry | E12: Glutes, Hamstrings, Calves | F12: Erector Spinae, Core, Quads | G12: Backpack, Weighted vest | H12: Common | I12: Hip Flexor — shortening under sustained load; Knee — patellofemoral on descents; Shoulder/Neck — pack fit | J12: Primary race-sim for foot legs; monitor foot hot spots; keep HR aerobic | K12: Stair climb with pack; Weighted vest walk; 🏠 Backpack loaded with books, water bottles, or bag of rice; weighted vest alternative: load a hydration pack with water | L12: EX009 — Farmer Carry; EX050 — Treadmill Incline Walk (Loaded Pack) | M12: Hip Flexor, Knee, Shoulder/Neck | N12: EX120 — Sustained LISS (Hiking Pace) | O12: EX050 — Treadmill Incline Walk (Loaded Pack) | P12: =COUNTIF('Sport-Exercise Map'!A:A,A12)
A13: EX011 | B13: Pallof Press (Band/Cable) | C13: Isometric | D13: Anti-Rotation | E13: Obliques, Transverse Abdominis | F13: Glutes, Hip Flexors | G13: Resistance band, Cable machine | H13: Common | I13: Shoulder — instability if set too wide; Lumbar — rotation if core not braced | J13: Anti-rotation; builds kayak/paddle torso stability; hips square throughout | K13: Half-kneeling band version (rotation not anti-rotation); Landmine Pallof; 🏠 Band anchored in closed door at chest height; or hug a heavy backpack and resist rotation standing | L13: EX089 — Hollow Body Hold; EX088 — Russian Twist (DB / Med Ball) | M13: Shoulder, Lumbar | N13: EX087 — Cable High-to-Low Chop | P13: =COUNTIF('Sport-Exercise Map'!A:A,A13)
A14: EX012 | B14: Copenhagen Plank | C14: Isometric | D14: Anti-Adduction, Single-Leg | E14: Hip Adductors, Obliques | F14: Glutes, Core | G14: Bench, Plyo box | H14: Specialized | I14: Groin — adductor strain if loaded too early; Hip — lateral capsule stress | J14: Top foot on bench; groin injury prevention; underused across most sports | K14: Side-lying hip adduction (no bench); Adductor squeeze (ball between knees); 🏠 Bed edge or chair seat for top foot elevation | L14: EX023 — Lateral Lunge (DB or BW); EX040 — Clamshell (Band) | M14: Groin, Hip | P14: =COUNTIF('Sport-Exercise Map'!A:A,A14)
A15: EX013 | B15: Hip Circle (Band) | C15: Activation / Primer | D15: Hip-Ext, Rotation | E15: Glute Med, Glute Max | F15: Hip Abductors | G15: Resistance band | H15: Common | I15: Hip — impingement at extreme range if rushed | J15: Pre-run/hike glute activation; controlled ROM not speed | K15: Standing hip circle without band; 🏠 Loop a towel or belt around knees as improvised band; no equipment for unresisted version | L15: EX040 — Clamshell (Band); EX039 — Glute Bridge (Double-Leg) | M15: Hip | N15: EX017 — Lateral Band Walk | P15: =COUNTIF('Sport-Exercise Map'!A:A,A15)
A16: EX014 | B16: World's Greatest Stretch | C16: Mobility | D16: Squat, Rotation, Hip-Ext | E16: Hip Flexors, Thoracic Spine, Hamstrings | F16: Glutes, Groin, Shoulders | H16: Common | I16: Knee — medial stress if front foot collapses; Wrist — load on hard surface | J16: Highest-yield single mobility drill; integrates lower and upper chain | K16: 🏠 No equipment needed | L16: EX015 — Pigeon Pose; EX046 — Hip Flexor Lunge Stretch | M16: Knee, Wrist | P16: =COUNTIF('Sport-Exercise Map'!A:A,A16)
A17: EX015 | B17: Pigeon Pose | C17: Flexibility / Stretching | D17: Hip-Ext | E17: Piriformis, Glutes, Hip External Rotators | F17: IT Band, Hip Flexors | H17: Common | I17: Knee — meniscus/ligament stress if torqued; Hip — SI joint irritation if pelvis not level | J17: Keep hips square; pad under hip if needed; 90s+ holds for tissue adaptation | K17: Supine figure-4 stretch (floor sub for pigeon); Thread-the-needle; 🏠 Folded towel under hip for comfort; hotel bed corner for elevated pigeon | L17: EX046 — Hip Flexor Lunge Stretch; EX014 — World's Greatest Stretch | M17: Knee, Hip | P17: =COUNTIF('Sport-Exercise Map'!A:A,A17)
A18: EX016 | B18: Thoracic Rotation Drill | C18: Mobility | D18: Rotation | E18: Thoracic Erectors, Obliques | F18: Lats, Rear Delts | H18: Common | I18: Lumbar — compensatory rotation if thoracic locked | J18: Side-lying or quadruped; keep hips still to isolate T-spine; critical for paddle and climbing | K18: Side-lying thoracic rotation (wall sub); 🏠 No equipment needed; lie on hotel bed for side-lying version | L18: EX065 — Scapular Wall Slide; EX014 — World's Greatest Stretch | M18: Lumbar | P18: =COUNTIF('Sport-Exercise Map'!A:A,A18)
A19: EX017 | B19: Lateral Band Walk | C19: Activation / Primer | D19: Hip-Ext, Abduction | E19: Glute Medius, Glute Minimus | F19: Hip Abductors, TFL | G19: Resistance band | H19: Common | I19: Knee — valgus if band too high pulls inward | J19: Band above knees for knee stability; below knee for more hip demand; pre-run staple | K19: Theraband substitution; Lateral walk without band (reduced stimulus); 🏠 Towel or belt loop around ankles; hair tie or rubber bands doubled as light resistance | L19: EX040 — Clamshell (Band); EX041 — Monster Walk (Band) | M19: Knee | N19: EX041 — Monster Walk (Band) | O19: EX040 — Clamshell (Band) | P19: =COUNTIF('Sport-Exercise Map'!A:A,A19)
A20: EX018 | B20: Foam Roll (IT Band / Quads / Lats) | C20: Recovery / Soft Tissue | D20: Stretch | E20: IT Band, Quadriceps, Lats | F20: TFL, Glutes | G20: Foam Roller | H20: Common | I20: Knee — avoid rolling directly on lateral knee; Hip — bursa near greater trochanter | J20: Slow passes; 10–20s on tender spots; post-run, post-bike, post-hike recovery | K20: Lacrosse ball (targeted); Massage gun; Stick roller; 🏠 Tennis ball, lacrosse ball, or water bottle for targeted rolling; rolled-up towel under IT band; massage gun if available | L20: EX015 — Pigeon Pose; EX046 — Hip Flexor Lunge Stretch | M20: Knee, Hip | P20: =COUNTIF('Sport-Exercise Map'!A:A,A20)
A21: EX019 | B21: Barbell Hip Thrust | C21: Strength | D21: Hip-Ext | E21: Glutes | F21: Hamstrings, Core, Hip Flexors | G21: Barbell, Bench | H21: Common | I21: Lumbar — hyperextension at top; Hip — anterior impingement with poor setup | J21: Drive through heels; full hip lock at top; best glute isolator before loaded carries | K21: Single-Leg Hip Thrust; KB Hip Thrust; Barbell on bench (no rack); 🏠 Single-leg hip thrust on hotel bed edge; backpack across hips for load | L21: EX039 — Glute Bridge (Double-Leg); EX004 — Single-Leg RDL (DB) | M21: Lumbar, Hip | O21: EX039 — Glute Bridge (Double-Leg) | P21: =COUNTIF('Sport-Exercise Map'!A:A,A21)
A22: EX020 | B22: Nordic Hamstring Curl | C22: Strength | D22: Hinge | E22: Hamstrings (eccentric emphasis) | F22: Glutes, Calves | H22: Specialized | I22: Hamstring — high DOMS initially; Knee — patellar tendon stress at full extension | J22: Most evidence-backed hamstring injury prevention drill; eccentric load; progress slowly | K22: Nordic on bed anchor (feet under bed frame); Sliding disc hamstring curl; 🏠 Feet anchored under bed frame or heavy dresser; towel-assisted Nordic on smooth floor | L22: EX117 — Loaded Step-Down (Eccentric Box); EX004 — Single-Leg RDL (DB) | M22: Hamstring, Knee | O22: EX003 — Romanian Deadlift (Barbell) | P22: =COUNTIF('Sport-Exercise Map'!A:A,A22)
A23: EX021 | B23: Bulgarian Split Squat (DB) | C23: Strength | D23: Single-Leg, Squat | E23: Quadriceps, Glutes | F23: Hamstrings, Hip Stabilisers, Core | G23: Dumbbell | H23: Common | I23: Knee — anterior pain if shin too vertical; Hip Flexor — impingement at bottom; Ankle — rear foot instability | J23: Rear foot elevated; front foot far enough forward to keep shin vertical; best overall lower body exercise for AR | K23: Barbell Bulgarian Split Squat (if rack available); Sandbag on shoulder; 🏠 Chair or bed edge for rear foot elevation; backpack for load; stair step as platform | L23: EX022 — Reverse Lunge (DB or BW); EX038 — Split Squat ISO Hold | M23: Knee, Hip Flexor, Ankle | N23: EX028 — Pistol Squat / Assisted Pistol | O23: EX022 — Reverse Lunge (DB or BW) | P23: =COUNTIF('Sport-Exercise Map'!A:A,A23)
A24: EX022 | B24: Reverse Lunge (DB or BW) | C24: Strength | D24: Single-Leg, Squat | E24: Quadriceps, Glutes | F24: Hamstrings, Hip Stabilisers | G24: Dumbbell, Kettlebell | H24: Common | I24: Knee — patellar tracking if step too short; Hip — anterior impingement at bottom | J24: Step back not forward — reduces knee shear; better proprioceptive challenge than forward lunge | K24: Barbell Reverse Lunge; Sandbag Lunge; 🏠 Backpack for load; gallon jugs in each hand | L24: EX038 — Split Squat ISO Hold; EX039 — Glute Bridge (Double-Leg) | M24: Knee, Hip | N24: EX021 — Bulgarian Split Squat (DB) | P24: =COUNTIF('Sport-Exercise Map'!A:A,A24)
A25: EX023 | B25: Lateral Lunge (DB or BW) | C25: Strength | D25: Single-Leg, Abduction | E25: Glutes, Quads, Groin | F25: Hamstrings, Hip Stabilisers | G25: Dumbbell, Kettlebell | H25: Common | I25: Groin — adductor strain if range increases too fast; Knee — medial stress if loading knee collapses | J25: Sit into hip of working leg; non-working leg stays straight; critical for lateral terrain and climbing moves | K25: Barbell Lateral Lunge; Bodyweight lateral lunge (no load); 🏠 Gallon jugs in each hand for light lateral lunge load | L25: EX012 — Copenhagen Plank; EX040 — Clamshell (Band) | M25: Groin, Knee | P25: =COUNTIF('Sport-Exercise Map'!A:A,A25)
A26: EX024 | B26: Step-Up High Box (Loaded) | C26: Strength | D26: Single-Leg, Hip-Ext | E26: Glutes, Quadriceps | F26: Hamstrings, Core | G26: Dumbbell, Barbell, Weighted vest | H26: Common | I26: Knee — anterior stress if pushing off bottom foot; Hip — flexor impingement at top if box too high | J26: Drive through heel of working foot only; don't push off bottom foot; use 20–24" box | K26: Barbell Step-Up; Loaded backpack step-up; 🏠 Stair step, park bench, or sturdy chair as box; backpack for load | L26: EX119 — Weighted Step-Up (High Box, Heavy Load); EX021 — Bulgarian Split Squat | M26: Knee, Hip | N26: EX119 — Weighted Step-Up (High Box, Heavy Load) | P26: =COUNTIF('Sport-Exercise Map'!A:A,A26)
A27: EX025 | B27: Single-Leg Calf Raise (Loaded) | C27: Strength | D27: Hip-Ext | E27: Gastrocnemius, Soleus | F27: Peroneal Muscles, Plantar Fascia | G27: Dumbbell, Kettlebell | H27: Common | I27: Achilles — tendinopathy risk with rapid load increase; Plantar Fascia — stress at push-off | J27: Full ROM: deep stretch at bottom, strong lockout at top; use step edge for full range | K27: Smith Machine Calf Raise; Leg Press calf raise; Barbell calf raise; 🏠 Stair edge for full ROM calf raise; curb; thick book on floor; doorway threshold | L27: EX026 — Seated Calf Raise; EX035 — Ankle Hops / Pogo Jumps | M27: Achilles, Plantar Fascia | N27: EX035 — Ankle Hops / Pogo Jumps | O27: EX026 — Seated Calf Raise | P27: =COUNTIF('Sport-Exercise Map'!A:A,A27)
A28: EX026 | B28: Seated Calf Raise | C28: Strength | D28: Hip-Ext | E28: Soleus | F28: Tibialis Posterior | G28: Barbell | H28: Common | I28: Achilles — tendon stress if loaded too heavy too fast | J28: Bent knee isolates soleus — the fatigue-limiting muscle in distance running and hiking; underrated | K28: Barbell across thighs (no machine); Smith Machine Seated Calf Raise; 🏠 Seated on chair with heavy backpack across knees; gallon jugs on thighs | L28: EX025 — Single-Leg Calf Raise (Loaded); EX035 — Ankle Hops / Pogo Jumps | M28: Achilles | N28: EX025 — Single-Leg Calf Raise (Loaded) | P28: =COUNTIF('Sport-Exercise Map'!A:A,A28)
A29: EX027 | B29: Tibialis Raise (Wall or Machine) | C29: Strength | D29: Hip-Ext | E29: Tibialis Anterior | F29: Extensor Digitorum Longus | G29: Resistance band | H29: Specialized | I29: Shin — anterior compartment DOMS on introduction; Ankle — dorsiflexion ROM restriction | J29: Heels against wall, dorsiflex toes toward shin; best shin splint prevention exercise; novel to most athletes | K29: Seated tibialis raise (plate on toe); Band dorsiflexion; 🏠 Heels on stair edge, dorsiflex toes toward shins; no equipment needed for wall version | L29: EX035 — Ankle Hops / Pogo Jumps; EX045 — Ankle Mobility Drill (Wall) | M29: Shin, Ankle | P29: =COUNTIF('Sport-Exercise Map'!A:A,A29)
A30: EX028 | B30: Pistol Squat / Assisted Pistol | C30: Strength | D30: Single-Leg, Squat | E30: Quadriceps, Glutes | F30: Hip Stabilisers, Core, Ankle Dorsiflexors | G30: TRX / suspension trainer | H30: Specialized | I30: Knee — high patellar tendon load at bottom; Ankle — dorsiflexion restriction limits depth; Hip — impingement at full squat | J30: Use TRX or pole assist until strong enough; ankle mobility usually the limiting factor; mimics steep descent and high-step climbing | K30: TRX-assisted Pistol Squat; Pole-assisted Pistol Squat; 🏠 Doorframe or chair back for balance assist; no equipment needed for bodyweight version | L30: EX021 — Bulgarian Split Squat (DB); EX043 — Single-Leg Balance Hold | M30: Knee, Ankle, Hip | O30: EX021 — Bulgarian Split Squat (DB) | P30: =COUNTIF('Sport-Exercise Map'!A:A,A30)
A31: EX029 | B31: Sled Push | C31: Power | D31: Locomotion | E31: Quadriceps, Glutes, Calves | F31: Core, Hip Flexors | G31: Weighted Sled | H31: Common | I31: Hip Flexor — at full extension during push; Achilles — loading on drive phase | J31: No eccentric — ideal for accumulating leg volume without soreness; great for AR base phase | K31: Band sprint drill (resistance band anchored behind); Prowler (same pattern) | L31: EX031 — Kettlebell Swing (Two-Hand); EX007 — Box Jump | M31: Hip Flexor, Achilles | N31: EX031 — Kettlebell Swing (Two-Hand) | P31: =COUNTIF('Sport-Exercise Map'!A:A,A31)
A32: EX030 | B32: Reverse Sled Drag | C32: Strength | D32: Single-Leg, Squat | E32: Quadriceps (eccentric), VMO | F32: Hip Flexors, Core | G32: Weighted Sled | H32: Specialized | I32: Knee — patellar tendon if too heavy; Quad — significant DOMS on introduction | J32: Walk backward with sled; mimics downhill braking load without injury risk; builds VMO eccentric control | K32: Band walk-back (resistance band substitution for sled) | L32: EX020 — Nordic Hamstring Curl; EX117 — Loaded Step-Down (Eccentric Box) | M32: Knee, Quad | P32: =COUNTIF('Sport-Exercise Map'!A:A,A32)
A33: EX031 | B33: Kettlebell Swing (Two-Hand) | C33: Power | D33: Hinge, Hip-Ext | E33: Glutes, Hamstrings | F33: Erector Spinae, Core, Forearms | G33: Kettlebell | H33: Common | I33: Lumbar — flexion if hip hinge breaks down; Shoulder — impingement if arms too high; Wrist — extension load at top | J33: Hip hinge drives swing — not a squat; keep lats engaged; float at top not a press; high metabolic demand | K33: DB Swing; Single-arm KB Swing; 🏠 Filled suitcase or heavy backpack for improvised KB swing (two-hand grip on handle); gallon jug | L33: EX032 — Jump Squat (BW or Light Load); EX007 — Box Jump | M33: Lumbar, Shoulder, Wrist | O33: EX029 — Sled Push | P33: =COUNTIF('Sport-Exercise Map'!A:A,A33)
A34: EX032 | B34: Jump Squat (BW or Light Load) | C34: Power | D34: Squat, Hip-Ext | E34: Glutes, Quadriceps | F34: Hamstrings, Calves, Core | G34: Weighted vest | H34: Common | I34: Ankle — landing impact; Knee — valgus on landing; Lumbar — axial compression (loaded version) | J34: Land soft with hip hinge; keep load < 20% 1RM if loaded; rate of force development is the goal | K34: Barbell Jump Squat (< 20% 1RM); Sandbag Jump Squat; 🏠 No equipment needed for bodyweight version; backpack for light load | L34: EX007 — Box Jump; EX031 — Kettlebell Swing (Two-Hand) | M34: Ankle, Knee, Lumbar | N34: EX007 — Box Jump | P34: =COUNTIF('Sport-Exercise Map'!A:A,A34)
A35: EX033 | B35: Depth Drop (Eccentric Landing Practice) | C35: Plyometric | D35: Squat, Single-Leg | E35: Quadriceps (eccentric), Glutes | F35: Hamstrings, Ankle Stabilisers | G35: Plyo box | H35: Specialized | I35: Knee — high load if landing stiff; Ankle — impact with poor mechanics; Achilles — reactive stress | J35: Step off box, stick landing quietly; progress to single-leg; teaches soft landing critical for downhill trail | K35: Stair step-off (lower height); Curb depth drop; 🏠 Stair step or curb for low-height depth drop; park bench (test stability) | L35: EX117 — Loaded Step-Down (Eccentric Box); EX020 — Nordic Hamstring Curl | M35: Knee, Ankle, Achilles | O35: EX007 — Box Jump | P35: =COUNTIF('Sport-Exercise Map'!A:A,A35)
A36: EX034 | B36: Lateral Bound | C36: Plyometric | D36: Single-Leg, Locomotion | E36: Glutes, Quads, Calves | F36: Hip Abductors, Core | H36: Common | I36: Ankle — inversion sprain on landing; Knee — valgus if glutes not engaged; Groin — adductor strain wide landing | J36: Single-leg takeoff and landing; stick each landing; mimics rocky trail lateral foot adjustment | K36: Lateral hop over line (marked floor); Mini hurdle lateral hop; 🏠 No equipment needed; mark landing targets with tape or shoes | L36: EX055 — Lateral Shuffle Sprint; EX023 — Lateral Lunge (DB or BW) | M36: Ankle, Knee, Groin | N36: EX036 — Running Bounds (Exaggerated Stride) | P36: =COUNTIF('Sport-Exercise Map'!A:A,A36)
A37: EX035 | B37: Ankle Hops / Pogo Jumps | C37: Plyometric | D37: Locomotion | E37: Gastrocnemius, Soleus, Plantar Fascia | F37: Tibialis Posterior, Peroneals | H37: Specialized | I37: Achilles — reactive overload if volume too high; Plantar Fascia — stress at push-off; Ankle — instability | J37: Minimal knee bend — all ankle; quick ground contact; builds ankle stiffness for running economy | K37: Jump rope (double-under rhythm sim); Rebounding on mini trampoline; 🏠 No equipment needed; any flat surface | L37: EX025 — Single-Leg Calf Raise (Loaded); EX027 — Tibialis Raise | M37: Achilles, Plantar Fascia, Ankle | N37: EX008 — Broad Jump | O37: EX026 — Seated Calf Raise | P37: =COUNTIF('Sport-Exercise Map'!A:A,A37)
A38: EX036 | B38: Running Bounds (Exaggerated Stride) | C38: Plyometric | D38: Single-Leg, Locomotion, Hip-Ext | E38: Glutes, Hamstrings, Hip Flexors | F38: Core, Calves | H38: Common | I38: Hip Flexor — at peak extension; Hamstring — at landing position if tight; Achilles — push-off demand | J38: Exaggerate flight phase; powerful push-off and high knee drive; builds stride power for uphills | K38: Uphill bounding (terrain sub); Resist band bounds (added resistance); 🏠 No equipment needed; hallway, parking lot, or park grass | L38: EX048 — Hill Repeats; EX031 — Kettlebell Swing (Two-Hand) | M38: Hip Flexor, Hamstring, Achilles | O38: EX034 — Lateral Bound | P38: =COUNTIF('Sport-Exercise Map'!A:A,A38)
A39: EX037 | B39: Wall Sit | C39: Isometric | D39: Squat | E39: Quadriceps (VMO) | F39: Glutes, Core | H39: Common | I39: Knee — patellar tendon stress at 90° hold; Lumbar — if back loses wall contact | J39: Thighs parallel to floor; progress by time then add vest or plate on thighs; excellent hotel exercise | K39: 🏠 Any wall; hotel room wall; add backpack on thighs for progression | L39: EX038 — Split Squat ISO Hold; EX002 — Goblet Squat held at depth | M39: Knee, Lumbar | N39: EX002 — Goblet Squat (DB/KB) | P39: =COUNTIF('Sport-Exercise Map'!A:A,A39)
A40: EX038 | B40: Split Squat ISO Hold | C40: Isometric | D40: Single-Leg, Squat | E40: Quadriceps, Glutes, Hip Flexors | F40: Core, Hip Stabilisers | G40: Dumbbell, Kettlebell | H40: Specialized | I40: Knee — anterior pain if front shin angles forward; Hip Flexor — stretch discomfort at bottom | J40: Hold bottom position of Bulgarian or reverse lunge; builds end-range stability for trail and climbing terrain | K40: Barbell split squat hold at bottom; Loaded sandbag version; 🏠 Chair seat for rear foot elevation; bed edge; no equipment for floor version | L40: EX037 — Wall Sit; EX043 — Single-Leg Balance Hold | M40: Knee, Hip Flexor | N40: EX021 — Bulgarian Split Squat (DB) | P40: =COUNTIF('Sport-Exercise Map'!A:A,A40)
A41: EX039 | B41: Glute Bridge (Double-Leg) | C41: Activation / Primer | D41: Hip-Ext | E41: Glutes | F41: Hamstrings, Core | G41: Resistance band, Barbell | H41: Common | I41: Lumbar — hyperextension at top if core disengaged; Hamstring — cramp if glutes don't fire | J41: Drive through heels; full hip lock at top; add band above knees for glute med activation | K41: Barbell Glute Bridge; Single-Leg Glute Bridge; Band above knees variant; 🏠 No equipment needed; backpack across hips for load | L41: EX040 — Clamshell (Band); EX013 — Hip Circle (Band) | M41: Lumbar, Hamstring | N41: EX019 — Barbell Hip Thrust | P41: =COUNTIF('Sport-Exercise Map'!A:A,A41)
A42: EX040 | B42: Clamshell (Band) | C42: Activation / Primer | D42: Abduction | E42: Glute Medius | F42: Glute Minimus, TFL | G42: Resistance band | H42: Common | I42: Hip — anterior impingement if range excessive; TFL — overactivation if hip flexors compensate | J42: Keep hips stacked; rotate only at hip — not pelvis; do before lateral band walk | K42: Lateral lying hip abduction without band; 🏠 Towel or belt loop around knees; no equipment for unresisted version | L42: EX013 — Hip Circle (Band); EX039 — Glute Bridge (Double-Leg) | M42: Hip, TFL | N42: EX017 — Lateral Band Walk | P42: =COUNTIF('Sport-Exercise Map'!A:A,A42)
A43: EX041 | B43: Monster Walk (Band) | C43: Activation / Primer | D43: Abduction, Locomotion | E43: Glute Medius, Glute Minimus | F43: Hip Abductors, TFL | G43: Resistance band | H43: Common | I43: Knee — valgus if band too heavy or too high on thigh | J43: Slight forward lean; wide enough steps to keep tension throughout; lateral → diagonal → forward | K43: Lateral walk without band (reduced stimulus); 🏠 Towel or belt loop around ankles; no equipment for unresisted version | L43: EX017 — Lateral Band Walk; EX040 — Clamshell (Band) | M43: Knee | O43: EX017 — Lateral Band Walk | P43: =COUNTIF('Sport-Exercise Map'!A:A,A43)
A44: EX042 | B44: Donkey Kick / Fire Hydrant | C44: Activation / Primer | D44: Hip-Ext, Abduction | E44: Glutes | F44: Core, Hip Stabilisers | G44: Resistance band | H44: Common | I44: Lumbar — rotation if core doesn't brace during kick; Hip — impingement at extreme range | J44: Quadruped position; brace core to prevent lumbar rotation; adds variety to glute activation | K44: 🏠 No equipment needed | L44: EX039 — Glute Bridge (Double-Leg); EX040 — Clamshell (Band) | M44: Lumbar, Hip | P44: =COUNTIF('Sport-Exercise Map'!A:A,A44)
A45: EX043 | B45: Single-Leg Balance Hold | C45: Balance / Proprioception | D45: Single-Leg | E45: Hip Stabilisers, Peroneals | F45: Glute Med, Core | G45: BOSU ball, Balance Disc | H45: Common | I45: Ankle — inversion stress on unstable surface; Hip — lateral drop if glute med weak | J45: Progress: flat → eyes closed → unstable surface → add reach; builds ankle proprioception for trail and climbing | K45: Balance disc; BOSU (see EX044); Wobble board | L45: EX044 — BOSU Single-Leg Squat; EX038 — Split Squat ISO Hold | M45: Ankle, Hip | N45: EX044 — BOSU Single-Leg Squat | P45: =COUNTIF('Sport-Exercise Map'!A:A,A45)
A46: EX044 | B46: BOSU Single-Leg Squat | C46: Balance / Proprioception | D46: Single-Leg, Squat | E46: Quadriceps, Glutes | F46: Hip Stabilisers, Ankle Stabilisers | G46: BOSU ball | H46: Specialized | I46: Ankle — inversion sprain risk on dome; Knee — tracking issues if hip stabilisers weak | J46: Dome side up; load gradually; reactive stability needed on rocky trail terrain | K46: Balance disc squat; Wobble board single-leg | L46: EX043 — Single-Leg Balance Hold; EX034 — Lateral Bound | M46: Ankle, Knee | O46: EX043 — Single-Leg Balance Hold | P46: =COUNTIF('Sport-Exercise Map'!A:A,A46)
A47: EX045 | B47: Ankle Mobility Drill (Wall) | C47: Mobility | D47: Stretch | E47: Ankle Dorsiflexors, Calf Complex | F47: Plantar Fascia, Achilles | H47: Common | I47: Achilles — mild stretch discomfort normal; sharp pain is not; Ankle — stiffness post-run | J47: Knee-to-wall drill; track distance as progress metric; restricted dorsiflexion limits squat depth and uphill running | K47: 🏠 Any wall; measure knee-to-wall distance with phone or ruler to track progress | L47: EX047 — Calf / Achilles Wall Stretch; EX014 — World's Greatest Stretch | M47: Achilles, Ankle | P47: =COUNTIF('Sport-Exercise Map'!A:A,A47)
A48: EX046 | B48: Hip Flexor Lunge Stretch | C48: Flexibility / Stretching | D48: Hip-Ext | E48: Iliopsoas, Rectus Femoris | F48: TFL, Hip Capsule | H48: Common | I48: Knee — pressure on kneeling leg; Lumbar — hyperextension if anterior pelvic tilt not controlled | J48: Posterior pelvic tilt first; then drive hips forward; hold 60–90s; critical after hiking and running | K48: 🏠 Folded towel or pillow under kneeling knee; bed edge for rear foot elevation (couch stretch position) | L48: EX015 — Pigeon Pose; EX076 — Couch Stretch (Cyclist Hip Flexor) | M48: Knee, Lumbar | P48: =COUNTIF('Sport-Exercise Map'!A:A,A48)
A49: EX047 | B49: Calf / Achilles Wall Stretch | C49: Flexibility / Stretching | D49: Stretch | E49: Gastrocnemius (straight leg), Soleus (bent knee) | F49: Plantar Fascia, Achilles Tendon | H49: Common | I49: Achilles — avoid aggressive stretch in tendinopathy; Plantar Fascia — sore in the morning | J49: Both versions: straight leg (gastroc) and bent knee (soleus); hold 60s+; after every run or hike | K49: 🏠 Stair edge or curb for deeper calf stretch; wall in any room | L49: EX025 — Single-Leg Calf Raise (Loaded) — eccentric; EX045 — Ankle Mobility Drill | M49: Achilles, Plantar Fascia | P49: =COUNTIF('Sport-Exercise Map'!A:A,A49)
A50: EX048 | B50: Hill Repeats | C50: Interval / Tempo | D50: Locomotion | E50: Glutes, Hamstrings, Calves | F50: Hip Flexors, Core | G50: Outdoor Hill, Treadmill | H50: Common | I50: Achilles — high load on uphill push-off; Calf — fatigue on volume; Hamstring — at extension | J50: 6–10% grade; RPE 8–9; walk/jog recovery down; flat substitute: treadmill 8–12% | K50: Treadmill at 8–12% incline (terrain sub); Stair climber; 🏠 Hotel or building stairs — walk/run up 3–5 flights, elevator or walk down, repeat; parking garage ramp; highway overpass | L50: EX073 — Threshold Intervals (Bike); EX050 — Treadmill Incline Walk | M50: Achilles, Calf, Hamstring | P50: =COUNTIF('Sport-Exercise Map'!A:A,A50)
A51: EX049 | B51: Strides (Flying Sprints) | C51: Interval / Tempo | D51: Locomotion | E51: Hip Flexors, Glutes, Hamstrings | F51: Calves, Core | G51: Treadmill | H51: Common | I51: Hamstring — sprint mechanics if form breaks; Achilles — at max push-off | J51: 100m accelerations to ~90% effort then decelerate; 4–6 reps; improves running economy without heavy fatigue | K51: Treadmill sprint intervals; Curved treadmill strides; 🏠 Hotel hallway (quiet hours permitting); parking lot; any flat 100m stretch | L51: EX178 — Tempo Run (Flat / Road); EX035 — Ankle Hops / Pogo Jumps | M51: Hamstring, Achilles | P51: =COUNTIF('Sport-Exercise Map'!A:A,A51)
A52: EX050 | B52: Treadmill Incline Walk (Loaded Pack) | C52: Loaded Carry | D52: Locomotion, Carry | E52: Glutes, Quads, Calves | F52: Erector Spinae, Core, Hip Flexors | G52: Treadmill, Backpack | H52: Common | I52: Hip Flexor — shortening under sustained load; Knee — patellofemoral on steep incline; Shoulder/Neck — pack hot spots | J52: 8–15% grade; 20–35 lb pack; RPE 5–6; primary hotel substitute for outdoor rucking | K52: Stair climb with pack; Weighted vest incline walk; 🏠 Hotel stairs with loaded backpack (walk up, elevator down); building stairwell with pack | L52: EX010 — Rucking (Weighted Hike); EX009 — Farmer Carry | M52: Hip Flexor, Knee, Shoulder/Neck | N52: EX010 — Rucking (Weighted Hike) | P52: =COUNTIF('Sport-Exercise Map'!A:A,A52)
A53: EX051 | B53: Uphill Running Technique Drill | C53: Technical / Skill | D53: Locomotion | E53: Hip Flexors, Glutes, Calves | F53: Core, Arms | G53: Outdoor Hill, Treadmill | H53: Common | I53: Achilles — if heel striking excessively on incline | J53: Shorten stride; increase cadence; drive knees high; lean from ankles not waist; practice power-hike transition | K53: Treadmill at high incline for uphill mechanics practice | L53: EX048 — Hill Repeats; EX215 — Extreme Gradient Uphill Pacing | M53: Achilles | P53: =COUNTIF('Sport-Exercise Map'!A:A,A53)
A54: EX052 | B54: Downhill Running Technique Drill | C54: Technical / Skill | D54: Locomotion, Single-Leg | E54: Quadriceps (eccentric), Tibialis Anterior | F54: Core, Ankle Stabilisers | G54: Outdoor Hill | H54: Common | I54: Knee — top AR injury site; high eccentric quad load; Ankle — inversion on uneven surface | J54: Lean slightly forward; quick light foot strikes; scan ahead; don't brake — let terrain come to you | K54: Steep treadmill (decline if available); Grass hill | L54: EX117 — Loaded Step-Down (Eccentric Box); EX033 — Depth Drop; EX020 — Nordic Hamstring Curl | M54: Knee, Ankle | P54: =COUNTIF('Sport-Exercise Map'!A:A,A54)
A55: EX053 | B55: Agility Ladder Drill | C55: Agility | D55: Locomotion | E55: Hip Flexors, Calves, Quads | F55: Core, Ankle Stabilisers | G55: Agility Ladder | H55: Common | I55: Ankle — inversion sprain at speed; Hip Flexor — strain if not warmed up | J55: Variety of patterns: single foot, lateral, ickey shuffle; slow → fast; quick foot placement on technical terrain | K55: Marked tape lines on floor; Sidewalk cracks as rungs | L55: EX034 — Lateral Bound; EX055 — Lateral Shuffle Sprint | M55: Ankle, Hip Flexor | P55: =COUNTIF('Sport-Exercise Map'!A:A,A55)
A56: EX054 | B56: T-Drill / 5-10-5 Cone Drill | C56: Agility | D56: Locomotion | E56: Glutes, Quads, Hip Abductors | F56: Core, Ankle Stabilisers, Hip Flexors | G56: Cones | H56: Common | I56: Ankle — cutting stress; Knee — valgus on deceleration and cut; Groin — adductor strain in wide cut | J56: Plant and push from outside foot; low centre of gravity on cuts; sudden direction changes in orienteering | L56: EX055 — Lateral Shuffle Sprint; EX056 — Reactive Direction Change Drill | M56: Ankle, Knee, Groin | P56: =COUNTIF('Sport-Exercise Map'!A:A,A56)
A57: EX055 | B57: Lateral Shuffle Sprint | C57: Agility | D57: Locomotion, Abduction | E57: Glute Med, Hip Abductors, Quads | F57: Core, Ankle Stabilisers | H57: Common | I57: Groin — adductor strain with wide steps; Knee — medial stress on deceleration | J57: Stay low; don't cross feet; explosive push from outside foot; weaving through terrain | L57: EX034 — Lateral Bound; EX053 — Agility Ladder Drill | M57: Groin, Knee | P57: =COUNTIF('Sport-Exercise Map'!A:A,A57)
A58: EX056 | B58: Reactive Direction Change Drill | C58: Agility | D58: Locomotion | E58: Glutes, Quads, Calves | F58: Core, Hip Stabilisers, Ankle | H58: Specialized | I58: Ankle — inversion on reactive cuts; Knee — valgus without warm-up | J58: Partner or audio cue triggers direction change; simulates reactive route decisions; progress to doing while reading a map card | L58: EX053 — Agility Ladder Drill; EX034 — Lateral Bound | M58: Ankle, Knee | P58: =COUNTIF('Sport-Exercise Map'!A:A,A58)
A59: EX057 | B59: Map Navigation Run | C59: Technical / Skill | D59: Locomotion | E59: Aerobic System | F59: Neck, Eyes, Cognitive Load | H59: Specialized | I59: Neck — sustained downward gaze fatigue; Ankle — distraction injury risk while reading map | J59: Run-navigate simultaneously; fold map to current section; thumb on position; start slow to build dual-task habit | L59: EX059 — Neck Isometric Hold; EX043 — Single-Leg Balance Hold | M59: Neck, Ankle | P59: =COUNTIF('Sport-Exercise Map'!A:A,A59)
A60: EX058 | B60: Compass Bearing Walk / Run | C60: Technical / Skill | D60: Locomotion | E60: Aerobic System | F60: Neck, Cognitive Load | H60: Specialized | I60: Ankle — distraction injury when eyes on compass not terrain | J60: Take bearing; pick attack point 200m; navigate there without looking down repeatedly; hold bearing while moving | L60: EX059 — Neck Isometric Hold; EX043 — Single-Leg Balance Hold | M60: Ankle | P60: =COUNTIF('Sport-Exercise Map'!A:A,A60)
A61: EX060 | B61: Single-Leg Press (Machine) | C61: Strength | D61: Single-Leg, Squat | E61: Quadriceps, Glutes | F61: Hamstrings, Calves | G61: Leg Press Machine | H61: Common | I61: Knee — valgus if foot too wide; Lumbar — flatten against pad; Achilles — at bottom | J61: Foot high on platform for glute; low for quad; single leg directly mimics pedaling asymmetry | K61: Leg Press (bilateral then unilateral); Hack Squat machine single-leg; 🏠 Wall sit (EX037) as machine-free substitute; chair-depth squat for ROM reference | L61: EX021 — Bulgarian Split Squat (DB); EX024 — Step-Up High Box | M61: Knee, Lumbar, Achilles | N61: EX021 — Bulgarian Split Squat (DB) | P61: =COUNTIF('Sport-Exercise Map'!A:A,A62)
A62: EX061 | B62: Good Morning (Barbell) | C62: Strength | D62: Hinge | E62: Hamstrings, Erector Spinae, Glutes | F62: Core, Lats | G62: Barbell | H62: Common | I62: Lumbar — high stress if back rounds; Hamstring — overstretching if too upright | J62: Neutral spine throughout; slight knee bend; builds hip hinge position held while climbing on the bike | K62: DB Good Morning; Safety Bar Good Morning; 🏠 Broomstick across shoulders for movement pattern; backpack for light load | L62: EX003 — Romanian Deadlift (Barbell); EX067 — MTB Attack Position Hold | M62: Lumbar, Hamstring | N62: EX003 — Romanian Deadlift (Barbell) | P62: =COUNTIF('Sport-Exercise Map'!A:A,A63)
A63: EX062 | B63: Banded Hip Flexion (Standing) | C63: Activation / Primer | D63: Hip-Ext | E63: Iliopsoas, Rectus Femoris | F63: TFL, Core | G63: Resistance band | H63: Specialized | I63: Hip — anterior impingement at high range; Lumbar — hyperextension if core doesn't stabilise | J63: Band anchored behind; drive knee up against resistance; mimics pull-up phase of pedal stroke — often neglected | K63: Cable Hip Flexion (cable at ankle); Band at lower position; 🏠 Band anchored to bed leg or door handle behind you; towel looped around foot and door handle | L63: EX019 — Barbell Hip Thrust; EX039 — Glute Bridge (Double-Leg) | M63: Hip, Lumbar | P63: =COUNTIF('Sport-Exercise Map'!A:A,A64)
A64: EX063 | B64: Terminal Knee Extension (TKE) | C64: Activation / Primer | D64: Single-Leg | E64: VMO (Vastus Medialis Oblique) | F64: Quad Complex | G64: Resistance band | H64: Specialized | I64: Knee — patellar tracking if band angle wrong | J64: Band behind knee; slight hip hinge; extend fully to engage VMO; preventive for knee tracking common in cyclists | K64: Cable TKE (ankle attachment); Band at different height; 🏠 Band anchored to chair or table leg behind knee | L64: EX025 — Single-Leg Calf Raise (Loaded); EX027 — Tibialis Raise | M64: Knee | P64: =COUNTIF('Sport-Exercise Map'!A:A,A65)
A65: EX064 | B65: Reverse Nordic Curl | C65: Strength | D65: Hinge | E65: Quadriceps (eccentric, Rectus Femoris) | F65: Hip Flexors | H65: Specialized | I65: Knee — patellar tendon high stress; Quad — extreme DOMS on introduction; Hip Flexor — stretch at bottom | J65: Kneel with feet anchored; lean back slowly; most people can't do full rep initially; eccentric quad control for downhill braking | K65: Sliding hamstring curl (eccentric only); Nordic on bench; 🏠 Feet anchored under bed frame; knee pad from folded towel or pillow | L65: EX030 — Reverse Sled Drag; EX020 — Nordic Hamstring Curl | M65: Knee, Quad, Hip Flexor | P65: =COUNTIF('Sport-Exercise Map'!A:A,A66)
A66: EX065 | B66: Scapular Wall Slide | C66: Mobility | D66: Pull-H | E66: Serratus Anterior, Lower Traps, Rhomboids | F66: Rotator Cuff, Mid Traps | H66: Common | I66: Shoulder — impingement if arms forced overhead beyond available range; Neck — upper trap dominance | J66: Back flat on wall; slide arms up maintaining contact; corrects forward-rounded shoulder posture from riding and paddling | K66: 🏠 Any wall; hotel room wall works fine | L66: EX016 — Thoracic Rotation Drill; EX066 — Band Pull-Apart | M66: Shoulder, Neck | P66: =COUNTIF('Sport-Exercise Map'!A:A,A67)
A67: EX066 | B67: Band Pull-Apart | C67: Activation / Primer | D67: Pull-H | E67: Rear Deltoids, Rhomboids, Mid Traps | F67: Rotator Cuff, Biceps | G67: Resistance band | H67: Common | I67: Shoulder — impingement if band too tight or range forced; Elbow — hyperextension with locked arms | J67: Arms at shoulder height; slow eccentric back; counteracts hunched posture from riding and paddling; pre-session staple | K67: 🏠 Towel or t-shirt stretched between hands (pull apart motion); no resistance but patterns the movement | L67: EX081 — Band Face Pull; EX065 — Scapular Wall Slide | M67: Shoulder, Elbow | P67: =COUNTIF('Sport-Exercise Map'!A:A,A68)
A68: EX067 | B68: MTB Attack Position Hold | C68: Isometric | D68: Hinge | E68: Hip Extensors, Core, Shoulder Stabilisers | F68: Quads, Hamstrings, Forearms | H68: Specialized | I68: Lumbar — rounding under fatigue; Shoulder — anterior strain if elbows lock; Wrist — extension load | J68: Hip hinge; soft knees; neutral spine; elbows slightly bent; hold 30–120s; trains the fatigue position causing late-race handling errors | K68: 🏠 No equipment needed; hotel room floor space; add backpack for load | L68: EX037 — Wall Sit; EX038 — Split Squat ISO Hold | M68: Lumbar, Shoulder, Wrist | P68: =COUNTIF('Sport-Exercise Map'!A:A,A69)
A69: EX068 | B69: Wrist Pronation / Supination (DB) | C69: Strength | D69: Pull-H | E69: Pronator Teres, Supinator | F69: Forearm Flexors and Extensors | G69: Dumbbell | H69: Specialized | I69: Wrist — extension strain in supination; Elbow — medial stress with heavy load | J69: Forearm supported; full ROM rotation; builds forearm endurance for handlebar micro-adjustments on rough trail | K69: Forearm on bench with light plate (same rotation pattern); 🏠 Broomstick held at one end for rotation drill; light hammer or mallet for wrist rotation | L69: EX111 — Reverse Wrist Curl (DB); EX104 — Rice Bucket Drill | M69: Wrist, Elbow | P69: =COUNTIF('Sport-Exercise Map'!A:A,A70)
A70: EX069 | B70: Neck Extension Strengthening (Plate / Band) | C70: Strength | D70: Anti-Flexion | E70: Cervical Extensors, Upper Trapezius | F70: Semispinalis, Splenius | G70: Weight plates, Resistance band | H70: Specialized | I70: Cervical Spine — strain if load too heavy; Neck — disc irritation if range forced | J70: Isometric hold in neutral cycling head position; builds neck endurance for trail scanning and technical descent focus | K70: Light weight plate on forehead; Band under chin; 🏠 Towel around forehead with manual resistance (push head back against towel); lie face down on bed with head off edge for gravity resistance | L70: EX059 — Neck Isometric Hold (Map Reading Position); EX067 — MTB Attack Position Hold | M70: Cervical Spine, Neck | P70: =COUNTIF('Sport-Exercise Map'!A:A,A71)
A71: EX070 | B71: Single-Leg Cycling Drill (Trainer) | C71: Technical / Skill | D71: Single-Leg, Hip-Ext | E71: Iliopsoas, Glutes, Quads, Hamstrings | F71: Calf, Core | G71: Bike trainer | H71: Specialized | I71: Knee — tracking stress if cleat not set correctly; Hip Flexor — fatigues quickly | J71: Unclip one foot; pedal with one leg 30–60s; feel dead spots at top and bottom; reveals and corrects pedaling inefficiency | L71: EX073 — Threshold Intervals (Bike); EX062 — Banded Hip Flexion (Standing) | M71: Knee, Hip Flexor | P71: =COUNTIF('Sport-Exercise Map'!A:A,A72)
A72: EX071 | B72: Cornering Technique Drill (MTB) | C72: Technical / Skill | D72: Locomotion | E72: Core, Hip Stabilisers | F72: Glutes, Forearms | G72: Mountain bike, Trail | H72: Specialized | I72: Shoulder/Wrist — crash risk on learning; Wrist — extension load in corners | J72: Outside pedal down and weighted; lean bike not body; look through corner to exit; start slow | L72: EX044 — BOSU Single-Leg Squat; EX017 — Lateral Band Walk | M72: Shoulder/Wrist, Wrist | P72: =COUNTIF('Sport-Exercise Map'!A:A,A73)
A73: EX072 | B73: Pump Track / Trail Feature Technique | C73: Technical / Skill | D73: Locomotion | E73: Glutes, Core, Shoulders | F73: Quads, Triceps, Hip Flexors | G73: Mountain bike, Pump Track | H73: Specialized | I73: Shoulder/Wrist — crash risk; Lumbar — repeated flexion-extension | J73: Generate speed from terrain without pedaling using body weight shift; builds rhythm for efficient trail riding | L73: EX031 — Kettlebell Swing (Two-Hand); EX032 — Jump Squat | M73: Shoulder/Wrist, Lumbar | P73: =COUNTIF('Sport-Exercise Map'!A:A,A74)
A74: EX073 | B74: Threshold Intervals (Bike) | C74: Interval / Tempo | D74: Locomotion | E74: Aerobic System, Quads, Glutes | F74: Core, Hip Flexors | G74: Road bike, Mountain bike, Bike trainer, TT Bike, Gravel bike | H74: Common | I74: Knee — patellofemoral stress at high power; Hip Flexor — fatigue at threshold | J74: 10–20 min at ~95% FTP / RPE 7–8; 1–2 reps; builds lactate threshold for sustained race climbs | K74: Rowing erg intervals (cross-training); Running threshold intervals; 🏠 Hotel stairs at sustained effort (climb continuously); running tempo equivalent | L74: EX178 — Tempo Run (Flat / Road); EX048 — Hill Repeats | M74: Knee, Hip Flexor | P74: =COUNTIF('Sport-Exercise Map'!A:A,A75)
A75: EX074 | B75: VO2 Max Intervals (Bike) | C75: Interval / Tempo | D75: Locomotion | E75: Aerobic System, Quads, Glutes | F75: Cardiovascular System | G75: Road bike, Mountain bike, Bike trainer, TT Bike, Gravel bike | H75: Common | I75: Cardiac — monitor if new to high intensity; Knee — high load at peak output | J75: 3–8 min at RPE 9–9.5; 3–5 reps equal rest; builds peak aerobic capacity; reduces race time on long climbs | K75: Rowing erg VO2; Running intervals at equivalent effort | L75: EX048 — Hill Repeats; EX073 — Threshold Intervals (Bike) | M75: Cardiac, Knee | P75: =COUNTIF('Sport-Exercise Map'!A:A,A76)
A76: EX075 | B76: Sweet Spot Training (Bike) | C76: Interval / Tempo | D76: Locomotion | E76: Aerobic System, Quads, Glutes | F76: Core, Hip Flexors | G76: Road bike, Mountain bike, Bike trainer, TT Bike, Gravel bike | H76: Common | I76: Hip Flexor — extended time in position; Knee — sustained load | J76: 88–93% FTP / RPE 6.5–7.5; 20–40 min blocks; highest training value per fatigue unit; backbone of AR bike prep | K76: Rowing erg sweet spot; Running sustained aerobic | L76: EX073 — Threshold Intervals (Bike); EX178 — Tempo Run (Flat / Road) | M76: Hip Flexor, Knee | P76: =COUNTIF('Sport-Exercise Map'!A:A,A77)
A77: EX076 | B77: Couch Stretch (Cyclist Hip Flexor) | C77: Flexibility / Stretching | D77: Hip-Ext | E77: Iliopsoas, Rectus Femoris | F77: TFL, Hip Capsule | G77: Bench | H77: Common | I77: Knee — pressure on kneeling surface; Lumbar — hyperextension if not controlled | J77: Back foot elevated on wall/bench; drive hips forward; pelvic tilt first; cyclists are chronically short here — do daily | K77: 🏠 Bed edge, chair, or wall for rear foot elevation; couch arm works well | L77: EX046 — Hip Flexor Lunge Stretch; EX015 — Pigeon Pose | M77: Knee, Lumbar | P77: =COUNTIF('Sport-Exercise Map'!A:A,A78)
A78: EX077 | B78: Doorway Pec Stretch | C78: Flexibility / Stretching | D78: Push-H | E78: Pectoralis Major, Pectoralis Minor | F78: Anterior Deltoid, Biceps | G78: Doorway | H78: Common | I78: Shoulder — anterior capsule stress if arm above 90°; Neck — strain if head protrudes | J78: Keep arm at 90°; gentle lean; hold 45–60s; reverses forward shoulder rounding from riding; do post-ride | K78: 🏠 Any doorway or wall corner | L78: EX065 — Scapular Wall Slide; EX096 — 90/90 Shoulder Stretch | M78: Shoulder, Neck | P78: =COUNTIF('Sport-Exercise Map'!A:A,A79)
A79: EX078 | B79: Single-Arm DB Row | C79: Strength | D79: Pull-H | E79: Latissimus Dorsi, Rhomboids | F79: Rear Delts, Biceps, Core | G79: Dumbbell, Bench | H79: Common | I79: Lumbar — rotation if core doesn't brace; Shoulder — anterior stress if elbow flares wide | J79: Brace on bench; pull elbow to hip not shoulder; builds unilateral pulling strength for paddle stroke | K79: Cable Row single-arm; Band Row single-arm; TRX Row; 🏠 Gallon jug row; suitcase row; towel anchored in closed door for inverted row | L79: EX079 — Seated Cable Row; EX006 — Pull-Up (BW) | M79: Lumbar, Shoulder | P79: =COUNTIF('Sport-Exercise Map'!A:A,A80)
A80: EX079 | B80: Seated Cable Row (Narrow Grip) | C80: Strength | D80: Pull-H | E80: Rhomboids, Mid Traps, Lats | F80: Rear Delts, Biceps | G80: Cable machine, Resistance band | H80: Common | I80: Lumbar — rounding under heavy load; Shoulder — impingement if elbows flare | J80: Tall posture; squeeze shoulder blades at end; mirrors catch-and-pull phase of forward paddle stroke | K80: Band Seated Row; TRX Row (bilateral); DB Row (bilateral); 🏠 Towel in closed door — sit on floor and row toward door; resistance band anchored to door handle | L80: EX078 — Single-Arm DB Row; EX080 — Lat Pulldown | M80: Lumbar, Shoulder | P80: =COUNTIF('Sport-Exercise Map'!A:A,A81)
A81: EX080 | B81: Lat Pulldown (Wide Grip) | C81: Strength | D81: Pull-V | E81: Latissimus Dorsi | F81: Rear Delts, Biceps, Core | G81: Cable machine | H81: Common | I81: Shoulder — anterior stress if pulled behind neck; Wrist — extension load with wide grip | J81: Pull to collarbone — never behind neck; lats power the high-to-low paddle and swim stroke arc | K81: Band Lat Pulldown; TRX Row (horizontal); Rope Lat Pulldown; 🏠 Towel over door-mount bar for lat pulldown motion; band over top of door | L81: EX006 — Pull-Up (BW); EX078 — Single-Arm DB Row | M81: Shoulder, Wrist | N81: EX006 — Pull-Up (BW) | O81: EX084 — Scapular Depression Hold | P81: =COUNTIF('Sport-Exercise Map'!A:A,A82)
A82: EX081 | B82: Band Face Pull | C82: Activation / Primer | D82: Pull-H | E82: Rear Deltoids, External Rotators, Mid Traps | F82: Rhomboids, Rotator Cuff | G82: Resistance band, Cable machine | H82: Common | I82: Shoulder — impingement if elbows drop below shoulder; Neck — strain if head protrudes | J82: Pull to forehead with elbows high; external rotate at end; rotator cuff health; counteracts internal rotation bias of paddling and swimming | K82: Cable Face Pull; Light DB prone rear delt raise; 🏠 Towel or t-shirt stretched between hands at face height; band anchored on door handle | L82: EX082 — External Rotation (Band / Cable); EX066 — Band Pull-Apart | M82: Shoulder, Neck | P82: =COUNTIF('Sport-Exercise Map'!A:A,A83)
A83: EX082 | B83: External Rotation (Band / Cable) | C83: Activation / Primer | D83: Pull-H | E83: Infraspinatus, Teres Minor (Rotator Cuff) | F83: Rear Deltoid | G83: Resistance band, Cable machine, Dumbbell | H83: Specialized | I83: Shoulder — impingement if loaded too heavily; Elbow — pad surface to protect | J83: Light load; slow and controlled; prevents most common kayak and swimming shoulder injury — anterior instability | K83: Light DB External Rotation; Prone rear delt raise (internal/external sim); 🏠 Gallon jug (light external rotation); towel through door handle for rotation resistance | L83: EX081 — Band Face Pull; EX066 — Band Pull-Apart | M83: Shoulder, Elbow | P83: =COUNTIF('Sport-Exercise Map'!A:A,A84)
A84: EX083 | B84: Serratus Punch | C84: Activation / Primer | D84: Push-H | E84: Serratus Anterior | F84: Pectorals, Triceps | G84: Dumbbell | H84: Specialized | I84: Shoulder — winging if serratus is weak (the problem this fixes); Neck — upper trap compensation | J84: Supine; arm up; punch ceiling by protracting scapula; prevents scapular winging — common cause of shoulder pain in paddling and swimming | K84: 🏠 No equipment needed for bodyweight serratus punch (lie on floor, punch ceiling with fist) | L84: EX084 — Scapular Depression Hold; EX109 — Scapular Pull-Up | M84: Shoulder, Neck | P84: =COUNTIF('Sport-Exercise Map'!A:A,A85)
A85: EX084 | B85: Scapular Depression Hold | C85: Isometric | D85: Pull-V | E85: Lower Trapezius, Serratus Anterior | F85: Rhomboids, Lats | G85: Pull-Up Bar, Rings | H85: Specialized | I85: Shoulder — impingement if done with existing impingement syndrome; Neck — upper trap dominance | J85: Dead hang; actively depress and retract shoulder blades without bending arms; 10–20s; builds scapular stability for paddle bracing and swim pull | K85: Gymnastics rings hang with scapular depression; TRX scapular depression | L85: EX005 — Dead Hang; EX109 — Scapular Pull-Up | M85: Shoulder, Neck | N85: EX005 — Dead Hang | P85: =COUNTIF('Sport-Exercise Map'!A:A,A86)
A86: EX085 | B86: Med Ball Rotational Throw (Wall) | C86: Power | D86: Rotation | E86: Obliques, Glutes, Thoracic Rotators | F86: Core, Lats, Hips | G86: Medicine Ball | H86: Common | I86: Lumbar — rotation under load; Shoulder — deceleration stress on follow-through; Wrist — impact on catch | J86: Stand perpendicular to wall; rotate and throw explosively; catch and repeat; builds rotational power for paddle and swim stroke drive phase | K86: Ball against wall if medicine ball unavailable; Band rotational throw; 🏠 Throw a heavy backpack or filled duffel against a concrete wall; sandbag against outdoor wall | L86: EX087 — Cable High-to-Low Chop; EX088 — Russian Twist (DB / Med Ball) | M86: Lumbar, Shoulder, Wrist | N86: EX086 — Landmine Rotation | O86: EX087 — Cable High-to-Low Chop | P86: =COUNTIF('Sport-Exercise Map'!A:A,A87)
A87: EX086 | B87: Landmine Rotation | C87: Power | D87: Rotation | E87: Obliques, Glutes, Thoracic Rotators | F87: Lats, Core, Shoulders | G87: Barbell, Landmine Attachment | H87: Specialized | I87: Lumbar — rotation under load; Shoulder — end-range stress at extended position | J87: Arc bar hip-to-hip; explosive hip drive; can load progressively; excellent paddle and swim power developer | K87: Barbell in corner (landmine improvised); DB rotational press | L87: EX085 — Med Ball Rotational Throw (Wall); EX087 — Cable High-to-Low Chop | M87: Lumbar, Shoulder | O87: EX085 — Med Ball Rotational Throw (Wall) | P87: =COUNTIF('Sport-Exercise Map'!A:A,A88)
A88: EX087 | B88: Cable High-to-Low Chop | C88: Strength | D88: Rotation | E88: Obliques, Core, Lats | F88: Glutes, Shoulders, Thoracic | G88: Cable machine, Resistance band | H88: Common | I88: Lumbar — rotation under excessive load; Shoulder — end-range strain if forced | J88: Set cable high; chop diagonally to opposite low hip; mimics paddle stroke plane exactly | K88: Band Chop (resistance band sub for cable); 🏠 Band anchored high on door for chop motion; broomstick with band | L88: EX085 — Med Ball Rotational Throw (Wall); EX088 — Russian Twist | M88: Lumbar, Shoulder | N88: EX085 — Med Ball Rotational Throw (Wall) | O88: EX088 — Russian Twist (DB / Med Ball) | P88: =COUNTIF('Sport-Exercise Map'!A:A,A89)
A89: EX088 | B89: Russian Twist (DB / Med Ball) | C89: Strength | D89: Rotation | E89: Obliques, Transverse Abdominis | F89: Hip Flexors, Core | G89: Dumbbell, Medicine Ball | H89: Common | I89: Lumbar — disc stress under rotation if too heavy; Hip Flexor — strain if held extended | J89: Lean back 45°; rotate slowly through full range; moderate weight — heavy is counterproductive here | K89: 🏠 Gallon water jug held at chest; filled backpack; no weight needed (bodyweight rotation) | L89: EX011 — Pallof Press (Band/Cable); EX087 — Cable High-to-Low Chop | M89: Lumbar, Hip Flexor | N89: EX087 — Cable High-to-Low Chop | P89: =COUNTIF('Sport-Exercise Map'!A:A,A90)
A90: EX089 | B90: Hollow Body Hold | C90: Isometric | D90: Anti-Extension | E90: Transverse Abdominis, Rectus Abdominis | F90: Hip Flexors, Serratus | H90: Common | I90: Lumbar — pressure if core can't maintain position; Hip Flexor — fatigues quickly if pelvis tilts | J90: Posterior pelvic tilt; lower back pressed to floor; arms overhead increases lever; braced core needed for boat stability and swim streamline | K90: 🏠 No equipment needed | L90: EX011 — Pallof Press (Band/Cable); EX037 — Wall Sit | M90: Lumbar, Hip Flexor | P90: =COUNTIF('Sport-Exercise Map'!A:A,A91)
A91: EX090 | B91: Paddling Ergometer Session | C91: Aerobic / Endurance | D91: Locomotion, Rotation | E91: Lats, Core, Shoulders, Obliques | F91: Triceps, Biceps, Forearms | G91: Paddle Ergometer | H91: Common | I91: Shoulder — impingement with poor stroke mechanics; Wrist — tendinitis with overuse; Lumbar — rotation fatigue | J91: Focus on torso rotation — not arm pull; catch early; exit at hip; builds paddling aerobic base and stroke conditioning | K91: Indoor rower (Concept2) with arm-only setting; Shadow paddle with band | L91: EX203 — Rowing Erg Interval Session; EX087 — Cable High-to-Low Chop | M91: Shoulder, Wrist, Lumbar | P91: =COUNTIF('Sport-Exercise Map'!A:A,A92)
A92: EX091 | B92: Forward Stroke Technique Drill | C92: Technical / Skill | D92: Locomotion, Rotation | E92: Obliques, Lats, Core | F92: Shoulders, Biceps | G92: Kayak / Packraft | H92: Common | I92: Shoulder — injury if catch too wide or arm-dominated; Wrist — flexor tendinitis with bent-wrist grip | J92: Rotate torso to plant paddle near feet; unwind torso to drive — not arms; exit at hip; highest-return technical improvement | L92: EX087 — Cable High-to-Low Chop; EX090 — Paddling Ergometer Session | M92: Shoulder, Wrist | P92: =COUNTIF('Sport-Exercise Map'!A:A,A93)
A93: EX092 | B93: Bracing Stroke Drill (High and Low) | C93: Technical / Skill | D93: Anti-Rotation, Balance / Proprioception | E93: Rotator Cuff, Core, Obliques | F93: Shoulder Stabilisers, Lats | G93: Kayak / Packraft | H93: Specialized | I93: Shoulder — high brace = arm above 90° + external rotation = vulnerable; Elbow — hyperextension if arm locks | J93: Keep elbow below wrist in high brace; low brace preferred when possible; most paddling shoulder injuries from poor brace mechanics | L93: EX082 — External Rotation (Band / Cable); EX084 — Scapular Depression Hold | M93: Shoulder, Elbow | P93: =COUNTIF('Sport-Exercise Map'!A:A,A94)
A94: EX093 | B94: Eskimo Roll Practice | C94: Technical / Skill | D94: Rotation, Balance / Proprioception | E94: Core, Obliques, Lats, Hip Flexors | F94: Shoulder, Rotator Cuff | G94: Kayak, Pool or Flat Water | H94: Specialized | I94: Shoulder — impingement in setup position; Neck — strain if tucking late; Knee — brace position in cockpit | J94: Hip snap drives the roll — not arms; C-to-C or sweep roll; not required for packraft but valuable for rescue confidence | L94: EX089 — Hollow Body Hold; EX082 — External Rotation (Band / Cable) | M94: Shoulder, Neck, Knee | P94: =COUNTIF('Sport-Exercise Map'!A:A,A95)
A95: EX094 | B95: Packraft Inflation / Deflation Drill | C95: Technical / Skill | D95: Locomotion | E95: Diaphragm, Lung Capacity | F95: Upper Body, Core | G95: Packraft | H95: Specialized | I95: Neck — strain with repeated neck inflation; Lungs — hyperventilation if rushing | J95: Timed practice for transition efficiency; oral inflation vs pump bag; deflation, fold, and pack; time is lost at packraft transitions | L95: EX089 — Hollow Body Hold; EX090 — Paddling Ergometer Session | M95: Neck, Lungs | P95: =COUNTIF('Sport-Exercise Map'!A:A,A96)
A96: EX095 | B96: Portage Carry Simulation | C96: Loaded Carry | D96: Carry | E96: Trapezius, Core, Glutes, Quads | F96: Erector Spinae, Shoulder Girdle, Calves | G96: Packraft, Backpack | H96: Specialized | I96: Shoulder — impingement from awkward carry position; Lumbar — asymmetric load; Neck — compression under boat weight | J96: Carry loaded packraft over rough terrain; practice boat-on-shoulder and bow-drag variations; builds specific tolerance for this transition | K96: Loaded backpack portage; Sandbag carry (shape sim); 🏠 Carry two loaded grocery bags plus a suitcase over rough ground; duffel bag over shoulder on uneven terrain | L96: EX009 — Farmer Carry; EX010 — Rucking (Weighted Hike) | M96: Shoulder, Lumbar, Neck | P96: =COUNTIF('Sport-Exercise Map'!A:A,A97)
A97: EX096 | B97: 90/90 Shoulder Stretch | C97: Flexibility / Stretching | D97: Push-H | E97: Pectoralis Minor, Anterior Capsule, Biceps Long Head | F97: Subscapularis, Coracobrachialis | G97: Bench | H97: Specialized | I97: Shoulder — anterior capsule strain with aggressive overpressure; Neck — strain if head not supported | J97: Arm at 90° at shoulder and elbow; let arm fall toward floor; hold 60–90s; opens anterior shoulder for safe bracing stroke and climbing overhead | K97: 🏠 Bed or floor; no equipment needed | L97: EX077 — Doorway Pec Stretch; EX097 — Pec Minor Stretch (Low Doorway) | M97: Shoulder, Neck | P97: =COUNTIF('Sport-Exercise Map'!A:A,A98)
A98: EX097 | B98: Pec Minor Stretch (Low Doorway) | C98: Flexibility / Stretching | D98: Push-H | E98: Pectoralis Minor | F98: Coracobrachialis, Anterior Deltoid | G98: Doorway | H98: Specialized | I98: Shoulder — anterior instability if overstretched; Neck — strain if compensating | J98: Arm low on doorframe below 90°; targets pec minor specifically; pec minor tightness rounds shoulders and restricts paddle and climbing reach | K98: 🏠 Any doorway | L98: EX077 — Doorway Pec Stretch; EX096 — 90/90 Shoulder Stretch | M98: Shoulder, Neck | P98: =COUNTIF('Sport-Exercise Map'!A:A,A99)
A99: EX098 | B99: DB Shoulder Press | C99: Strength | D99: Push-V | E99: Anterior Deltoid, Triceps | F99: Lateral Deltoid, Core, Upper Traps | G99: Dumbbell | H99: Common | I99: Shoulder — impingement above 90° if internal rotation present; Lumbar — hyperextension under heavy load; Wrist — extension load | J99: Neutral or slight forward arm angle; don't flare elbows; builds overhead stability for high brace recovery and paddle exit | K99: KB Overhead Press; Barbell Overhead Press; Band Overhead Press; 🏠 Gallon water jugs pressed overhead; backpack held overhead for time (isometric) | L99: EX099 — External Rotation to Press; EX082 — External Rotation (Band / Cable) | M99: Shoulder, Lumbar, Wrist | P99: =COUNTIF('Sport-Exercise Map'!A:A,A100)
A100: EX099 | B100: External Rotation to Press (Band / Cable) | C100: Strength | D100: Push-V, Pull-H | E100: Rotator Cuff, Anterior Deltoid, Triceps | F100: Mid Traps, Rear Delts | G100: Resistance band, Cable machine | H100: Specialized | I100: Shoulder — overload if band too stiff; Wrist — extension load | J100: Externally rotate from 90° elbow bent; then press overhead; trains full shoulder arc of paddle high exit and recovery phase | K100: Band version (resistance band sub for cable) | L100: EX098 — DB Shoulder Press; EX082 — External Rotation (Band / Cable) | M100: Shoulder, Wrist | P100: =COUNTIF('Sport-Exercise Map'!A:A,A101)
...

Sheet Sport-Exercise Map
A1: ADVENTURE RACING — SPORT-EXERCISE CROSS REFERENCE
A2: Exercise ID | B2: Exercise Name | C2: Exercise Type | D2: Sport | E2: Sport Relevance Note | F2: Priority
A3: EX001 | B3: Back Squat (Barbell) | C3: Strength | D3: Trail Running | E3: Primary lower body strength builder; powers uphill drive and controls eccentric descent load under pack | F3: High
A4: EX002 | B4: Goblet Squat (DB/KB) | C4: Strength | D4: Trail Running | E4: Hotel substitute for back squat; same sport carryover with less equipment | F4: High
A5: EX003 | B5: Romanian Deadlift (Barbell) | C5: Strength | D5: Trail Running | E5: Hamstring and glute loading for push-off power and descent control; posterior chain base | F5: High
A6: EX004 | B6: Single-Leg RDL (DB) | C6: Strength | D6: Trail Running | E6: Unilateral posterior chain; directly mirrors single-leg braking mechanics on trail descents | F6: High
A7: EX007 | B7: Box Jump | C7: Plyometric | D7: Trail Running | E7: Explosive hip extension for steep uphill transitions and obstacle clearance | F7: High
A8: EX008 | B8: Broad Jump | C8: Plyometric | D8: Trail Running | E8: Horizontal power output; stream crossings, obstacle hops; also a field test metric | F8: High
A9: EX009 | B9: Farmer Carry | C9: Loaded Carry | D9: Trail Running | E9: Pack carry simulation; builds grip, trap, and core endurance under sustained load | F9: Medium
A10: EX010 | B10: Rucking (Weighted Hike) | C10: Loaded Carry | D10: Trail Running | E10: Direct race sim for foot legs; primary training modality for AR pack adaptation | F10: Critical
A11: EX011 | B11: Pallof Press (Band/Cable) | C11: Isometric | D11: Trail Running | E11: Core anti-rotation under load; controls lateral trunk sway with heavy pack | F11: Medium
A12: EX012 | B12: Copenhagen Plank | C12: Isometric | D12: Trail Running | E12: Groin and adductor strength for lateral terrain demands and hip stability under fatigue | F12: High
A13: EX013 | B13: Hip Circle (Band) | C13: Activation / Primer | D13: Trail Running | E13: Pre-run glute activation; ensures glutes fire before demand is placed on the kinetic chain | F13: High
... A1010: EX230 | B1010: Conventional Deadlift (Barbell) | C1010: Strength | D1010: Marathon | E1010: Posterior chain strength base; the hip hinge pattern underlies every running push-off across 26.2 miles | F1010: High

Sheet Sport Summary
A1: EXERCISES BY SPORT — QUICK REFERENCE
A2: Trail Running | D2: Orienteering | G2: Mountain Biking | J2: Packrafting | M2: Rock Climbing | P2: Hiking | S2: Swimming | V2: Rappelling / Abseiling | Y2: Fixed Rope / Via Ferrata | AA2: XC / AR Cycling | AD2: Mountaineering | AG2: Snowshoeing | AI2: Kayaking | AL2: Canoeing | AO2: Paddle Rafting | AQ2: SkiMo | AS2: Triathlon | AU2: Marathon | AX2: Ultramarathon | AZ2: Road Cycling | BC2: Gravel Cycling | BF2: Bikepacking | BH2: Fencing | BK2: Obstacle Course Racing | BN2: Modern Pentathlon | BP2: Run-Bike-Run Duathlon | BS2: SwimRun | BU2: Rowing | BX2: XC Skiing | CA2: SUP | CC2: Long Distance Paddle Racing | CF2: Long Distance Orienteering | CI2: Multi-Sport Race | CK2: Mountain Running / Sky Running | CN2: Fell Running | CP2: General Conditioning
A3: Priority | B3: Exercise | D3: Priority | E3: Exercise | G3: Priority | H3: Exercise | J3: Priority | K3: Exercise | M3: Priority | N3: Exercise | P3: Priority | Q3: Exercise | S3: Priority | T3: Exercise | V3: Priority | W3: Exercise | Y3: Priority | Z3: Exercise | AA3: Priority | AB3: Exercise | AD3: Priority | AE3: Exercise | AG3: Priority | AH3: Exercise | AI3: Priority | AJ3: Exercise | AL3: Priority | AM3: Exercise | AO3: Priority | AP3: Exercise | AQ3: Priority | AR3: Exercise | AS3: Priority | AT3: Exercise | AU3: Priority | AV3: Exercise | AX3: Priority | AY3: Exercise | AZ3: Priority | BA3: Exercise | BC3: Priority | BD3: Exercise | BF3: Priority | BG3: Exercise | BH3: Priority | BI3: Exercise | BK3: Priority | BL3: Exercise | BN3: Priority | BO3: Exercise | BP3: Priority | BQ3: Exercise | BS3: Priority | BT3: Exercise | BU3: Priority | BV3: Exercise | BX3: Priority | BY3: Exercise | CA3: Priority | CB3: Exercise | CC3: Priority | CD3: Exercise | CF3: Priority | CG3: Exercise | CI3: Priority | CJ3: Exercise | CK3: Priority | CL3: Exercise | CN3: Priority | CO3: Exercise | CP3: Priority | CQ3: Exercise
A4: Critical | B4: EX010 — Rucking (Weighted Hike) | D4: Critical | E4: EX053 — Agility Ladder Drill | G4: Critical | H4: EX073 — Threshold Intervals (Bike) | J4: Critical | K4: EX090 — Paddling Ergometer Session | M4: Critical | N4: EX005 — Dead Hang | P4: Critical | Q4: EX010 — Rucking (Weighted Hike) | S4: Critical | T4: EX127 — Band Swimming Shoulder Prehab (Y-T-W-L) | V4: Critical | W4: EX130 — Rappel Device Operation Drill | Y4: Critical | Z4: EX134 — Ascender / Jumar Technique Drill | AA4: Critical | AB4: EX144 — Hike-a-Bike Carry Drill | AD4: Critical | AE4: EX148 — Crampon Walking Technique | AG4: Critical | AH4: EX153 — Snowshoe Gait Technique | AI4: Critical | AJ4: EX158 — Whitewater Line Reading | AL4: Critical | AM4: EX156 — Sweep Stroke Technique Drill | AO4: Critical | AP4: EX158 — Whitewater Line Reading | AQ4: Critical | AR4: EX168 — Skinning Uphill Technique | AS4: Critical | AT4: EX174 — Aero / TT Position Hold | AU4: Critical | AV4: EX178 — Tempo Run (Flat / Road) | AX4: Critical | AY4: EX180 — Walk-Run Interval Method (Ultra Pacing) | AZ4: Critical | BA4: EX184 — Road Cycling Descending Technique | BC4: Critical | BD4: EX185 — Climb Pacing & Cadence Management | BF4: Critical | BG4: EX185 — Climb Pacing & Cadence Management | BH4: Critical | BI4: EX190 — En Garde Position Hold | BK4: Critical | BL4: EX195 — Rope Climb | BN4: Critical | BO4: EX190 — En Garde Position Hold | BP4: Critical | BQ4: EX197 — Double Brick / Run-Bike-Run Pacing Drill | BS4: Critical | BT4: EX198 — Running in Wetsuit (SwimRun) | BU4: Critical | BV4: EX200 — Rowing Drive Sequence Drill | BX4: Critical | BY4: EX205 — Classic Diagonal Stride Technique | CA4: Critical | CB4: EX209 — SUP Forward Stroke Technique | CC4: Critical | CD4: EX160 — Seated Paddling Position Endurance | CF4: Critical | CG4: EX057 — Map Navigation Run | CI4: Critical | CJ4: EX175 — Brick Run Drill (Bike-to-Run Transition) | CK4: Critical | CL4: EX212 — Scrambling Technique (Moving Terrain) | CN4: Critical | CO4: EX214 — Fell Descent Technique (Steep Grass, Bog, Heather) | CP4: Critical | CQ4: EX216 — Plank (Front)
A5: Critical | B5: EX021 — Bulgarian Split Squat (DB) | D5: Critical | E5: EX056 — Reactive Direction Change Drill | G5: Critical | H5: EX074 — VO2 Max Intervals (Bike) | J5: Critical | K5: EX091 — Forward Stroke Technique Drill | M5: Critical | N5: EX006 — Pull-Up (BW) | P5: Critical | Q5: EX120 — Sustained LISS (Hiking Pace) | S5: Critical | T5: EX082 — External Rotation (Band / Cable) | V5: Critical | W5: EX131 — Wall Walk Descent Technique | Y5: Critical | Z5: EX135 — Via Ferrata Progressive Clip Drill | AA5: Critical | AB5: EX145 — Loaded Bike Low-Speed Balance Drill | AD5: Critical | AE5: EX149 — Ice Axe Self-Arrest | AG5: Critical | AH5: EX154 — Plunge Step Descent (Snowshoe) | AI5: Critical | AJ5: EX159 — Wet Exit & Re-entry (Kayak) | AL5: Critical | AM5: EX157 — Draw Stroke & Pry Technique | AO5: Critical | AP5: EX164 — High-Side Command Response Drill | AQ5: Critical | AR5: EX169 — Ski Kick-Turn on Slope | AS5: Critical | AT5: EX175 — Brick Run Drill (Bike-to-Run Transition) | AU5: Critical | AV5: EX179 — Marathon Pace Run | AX5: Critical | AY5: EX181 — On-the-Run Fueling Drill | AZ5: Critical | BA5: EX185 — Climb Pacing & Cadence Management | BC5: Critical | BD5: EX187 — Gravel Surface Reading & Line Selection | BF5: Critical | BG5: EX188 — Loaded Touring / Bikepacking Bike Handling | BH5: Critical | BI5: EX191 — Fencing Lunge & Recovery | BK5: Critical | BL5: EX196 — Obstacle Vault & Wall Traversal | BN5: Critical | BO5: EX191 — Fencing Lunge & Recovery | BP5: Critical | BQ5: EX175 — Brick Run Drill (Bike-to-Run Transition) | BS5: Critical | BT5: EX199 — SwimRun Water Entry & Exit Technique | BU5: Critical | BV5: EX201 — Catch Position Hold (Rowing) | BX5: Critical | BY5: EX206 — Skate Skiing V1 & V2 Technique | CA5: Critical | CB5: EX210 — SUP Standing Balance & Stability Drill | CC5: Critical | CD5: EX091 — Forward Stroke Technique Drill | CF5: Critical | CG5: EX058 — Compass Bearing Walk / Run | CI5: Critical | CJ5: EX176 — Triathlon Transition Practice (T1 & T2) | CK5: Critical | CL5: EX213 — Scree Running Descent Technique | CN5: Critical | CO5: EX215 — Extreme Gradient Uphill Pacing (VK / Sky Technique) | CP5: Critical | CQ5: EX217 — Dead Bug
A6: Critical | B6: EX025 — Single-Leg Calf Raise (Loaded) | D6: Critical | E6: EX057 — Map Navigation Run | G6: Critical | H6: EX075 — Sweet Spot Training (Bike) | J6: Critical | K6: EX082 — External Rotation (Band / Cable) | M6: Critical | N6: EX100 — Hangboard Half-Crimp Hold | P6: Critical | Q6: EX021 — Bulgarian Split Squat (DB) | S6: High | T6: EX126 — Freestyle Pull (With Buoy) | V6: Critical | W6: EX132 — Anchor Setup & Inspection | Y6: Critical | Z6: EX136 — Fixed Rope Body Position & Rest Drill | AA6: Critical | AB6: EX146 — Navigation While Cycling Drill | AD6: Critical | AE6: EX150 — Rest Step Technique | AG6: Critical | AH6: EX010 — Rucking (Weighted Hike) | AI6: Critical | AJ6: EX166 — Ferry & Eddy Turn Technique | AL6: Critical | AM6: EX158 — Whitewater Line Reading | AO6: Critical | AP6: EX165 — Raft Paddle Synchronisation & Power Phase | AQ6: Critical | AR6: EX170 — SkiMo Race Transition Drill | AS6: Critical | AT6: EX176 — Triathlon Transition Practice (T1 & T2) | AU6: Critical | AV6: EX181 — On-the-Run Fueling Drill | AX6: Critical | AY6: EX182 — Night Running & Low-Light Technique | AZ6: Critical | BA6: EX189 — Road & Gravel Paceline Technique | BC6: Critical | BD6: EX147 — Loose Surface Threshold Braking | BF6: Critical | BG6: EX144 — Hike-a-Bike Carry Drill | BH6: Critical | BI6: EX192 — Fencing Advance-Retreat Footwork Drill | BK6: Critical | BL6: EX006 — Pull-Up (BW) | BN6: Critical | BO6: EX192 — Fencing Advance-Retreat Footwork Drill | BP6: Critical | BQ6: EX073 — Threshold Intervals (Bike) | BS6: Critical | BT6: EX126 — Freestyle Pull (With Buoy) | BU6: Critical | BV6: EX203 — Rowing Erg Interval Session | BX6: Critical | BY6: EX207 — Double Pole Technique (XC Skiing) | CA6: Critical | CB6: EX016 — Thoracic Rotation Drill | CC6: Critical | CD6: EX090 — Paddling Ergometer Session | CF6: Critical | CG6: EX059 — Neck Isometric Hold (Map Reading Position) | CI6: Critical | CJ6: EX197 — Double Brick / Run-Bike-Run Pacing Drill | CK6: Critical | CL6: EX215 — Extreme Gradient Uphill Pacing (VK / Sky Technique) | CN6: Critical | CO6: EX052 — Downhill Running Technique Drill | CP6: Critical | CQ6: EX218 — Bird-Dog
A7: Critical | B7: EX048 — Hill Repeats | D7: Critical | E7: EX058 — Compass Bearing Walk / Run | G7: Critical | H7: EX067 — MTB Attack Position Hold | J7: Critical | K7: EX092 — Bracing Stroke Drill | M7: Critical | N7: EX101 — Hangboard Open-Hand Hold | P7: Critical | Q7: EX024 — Step-Up High Box (Loaded) | S7: High | T7: EX128 — Kicking Drill (Flutter / Frog) | V7: High | W7: EX133 — Brake Hand Squeeze Hold | Y7: Critical | Z7: EX005 — Dead Hang | AA7: Critical | AB7: EX073 — Threshold Intervals (Bike) | AD7: Critical | AE7: EX010 — Rucking (Weighted Hike) | AG7: Critical | AH7: EX120 — Sustained LISS (Hiking Pace) | AI7: Critical | AJ7: EX090 — Paddling Ergometer Session | AL7: Critical | AM7: EX161 — J-Stroke Technique | AO7: High | AP7: EX160 — Seated Paddling Position Endurance | AQ7: Critical | AR7: EX171 — Touring Ski Descent Technique | AS7: Critical | AT7: EX126 — Freestyle Pull (With Buoy) | AU7: Critical | AV7: EX025 — Single-Leg Calf Raise (Loaded) | AX7: Critical | AY7: EX183 — Running with Poles (Trail / Ultra) | AZ7: Critical | BA7: EX073 — Threshold Intervals (Bike) | BC7: Critical | BD7: EX073 — Threshold Intervals (Bike) | BF7: Critical | BG7: EX145 — Loaded Bike Low-Speed Balance Drill | BH7: Critical | BI7: EX021 — Bulgarian Split Squat (DB) | BK7: Critical | BL7: EX005 — Dead Hang | BN7: Critical | BO7: EX194 — Laser-Run Drill (Run-to-Shoot Transition) | BP7: Critical | BQ7: EX075 — Sweet Spot Training (Bike) | BS7: Critical | BT7: EX127 — Band Swimming Shoulder Prehab (Y-T-W-L) | BU7: Critical | BV7: EX204 — On-Water Boat Balance Drill | BX7: Critical | BY7: EX019 — Barbell Hip Thrust | CA7: High | CB7: EX211 — SUP Downwind & Wave Reading | CC7: Critical | CD7: EX161 — J-Stroke Technique | CF7: Critical | CG7: EX010 — Rucking (Weighted Hike) | CI7: Critical | CJ7: EX021 — Bulgarian Split Squat (DB) | CK7: Critical | CL7: EX052 — Downhill Running Technique Drill | CN7: Critical | CO7: EX021 — Bulgarian Split Squat (DB) | CP7: Critical | CQ7: EX219 — Side Plank
A8: Critical | B8: EX051 — Uphill Running Technique Drill | D8: High | E8: EX010 — Rucking (Weighted Hike) | G8: Critical | H8: EX070 — Single-Leg Cycling Drill (Trainer) | J8: Critical | K8: EX016 — Thoracic Rotation Drill | M8: Critical | N8: EX105 — Finger Extension (Band) | P8: Critical | Q8: EX117 — Loaded Step-Down (Eccentric Box) | S8: High | T8: EX129 — Swim-Specific Rotational Core (Dry Land) | V8: High | W8: EX005 — Dead Hang | Y8: Critical | Z8: EX006 — Pull-Up (BW) | AA8: Critical | AB8: EX075 — Sweet Spot Training (Bike) | AD8: Critical | AE8: EX120 — Sustained LISS (Hiking Pace) | AG8: High | AH8: EX155 — Snowshoe Sidehill Traverse & Kickturn | AI8: Critical | AJ8: EX091 — Forward Stroke Technique Drill | AL8: Critical | AM8: EX162 — Tandem Canoe Coordination Drill | AO8: High | AP8: EX157 — Draw Stroke & Pry Technique | AQ8: Critical | AR8: EX173 — Tuck Position Isometric Hold | AS8: Critical | AT8: EX127 — Band Swimming Shoulder Prehab (Y-T-W-L) | AU8: Critical | AV8: EX021 — Bulgarian Split Squat (DB) | AX8: Critical | AY8: EX021 — Bulgarian Split Squat (DB) | AZ8: Critical | BA8: EX075 — Sweet Spot Training (Bike) | BC8: Critical | BD8: EX075 — Sweet Spot Training (Bike) | BF8: Critical | BG8: EX075 — Sweet Spot Training (Bike) | BH8: Critical | BI8: EX056 — Reactive Direction Change Drill | BK8: Critical | BL8: EX009 — Farmer Carry | BN8: Critical | BO8: EX193 — Shooting Breath Control & Stance | BP8: Critical | BQ8: EX178 — Tempo Run (Flat / Road) | BS8: Critical | BT8: EX141 — Wetsuit Swimming Technique | BU8: Critical | BV8: EX001 — Back Squat (Barbell) | BX8: Critical | BY8: EX023 — Lateral Lunge (DB or BW) | CA8: High | CB8: EX090 — Paddling Ergometer Session | CC8: Critical | CD8: EX162 — Tandem Canoe Coordination Drill | CF8: Critical | CG8: EX120 — Sustained LISS (Hiking Pace) | CI8: Critical | CJ8: EX076 — Couch Stretch (Cyclist Hip Flexor) | CK8: Critical | CL8: EX051 — Uphill Running Technique Drill | CN8: Critical | CO8: EX117 — Loaded Step-Down (Eccentric Box) | CP8: Critical | CQ8: EX220 — Superman / Back Extension (BW)
A9: Critical | B9: EX052 — Downhill Running Technique Drill | D9: High | E9: EX008 — Broad Jump | G9: Critical | H9: EX076 — Couch Stretch (Cyclist Hip Flexor) | J9: High | K9: EX005 — Dead Hang | M9: Critical | N9: EX106 — Lock-Off Hold (90°, 120°) | P9: Critical | Q9: EX119 — Weighted Step-Up (High Box, Heavy Load) | S9: High | T9: EX006 — Pull-Up (BW) | V9: High | W9: EX006 — Pull-Up (BW) | Y9: High | Z9: EX019 — Barbell Hip Thrust | AA9: Critical | AB9: EX070 — Single-Leg Cycling Drill (Trainer) | AD9: Critical | AE9: EX119 — Weighted Step-Up (High Box, Heavy Load) | AG9: High | AH9: EX021 — Bulgarian Split Squat (DB) | AI9: Critical | AJ9: EX082 — External Rotation (Band / Cable) | AL9: Critical | AM9: EX163 — Canoe Portage Yoke Carry | AO9: High | AP9: EX156 — Sweep Stroke Technique Drill | AQ9: Critical | AR9: EX148 — Crampon Walking Technique | AS9: Critical | AT9: EX140 — Open Water Sighting Drill | AU9: Critical | AV9: EX035 — Ankle Hops / Pogo Jumps | AX9: Critical | AY9: EX020 — Nordic Hamstring Curl | AZ9: Critical | BA9: EX069 — Neck Extension Strengthening | BC9: Critical | BD9: EX076 — Couch Stretch (Cyclist Hip Flexor) | BF9: Critical | BG9: EX120 — Sustained LISS (Hiking Pace) | BH9: Critical | BI9: EX046 — Hip Flexor Lunge Stretch | BK9: High | BL9: EX078 — Single-Arm DB Row | BN9: Critical | BO9: EX126 — Freestyle Pull (With Buoy) | BP9: Critical | BQ9: EX021 — Bulgarian Split Squat (DB) | BS9: Critical | BT9: EX140 — Open Water Sighting Drill | BU9: Critical | BV9: EX089 — Hollow Body Hold | BX9: Critical | BY9: EX017 — Lateral Band Walk | CA9: High | CB9: EX087 — Cable High-to-Low Chop | CC9: Critical | CD9: EX095 — Portage Carry Simulation | CF9: Critical | CG9: EX180 — Walk-Run Interval Method (Ultra Pacing) | CI9: High | CJ9: EX178 — Tempo Run (Flat / Road) | CK9: Critical | CL9: EX048 — Hill Repeats | CN9: Critical | CO9: EX020 — Nordic Hamstring Curl | CP9: Critical | CQ9: EX228 — Push-Up (Bodyweight)
A10: High | B10: EX001 — Back Squat (Barbell) | D10: High | E10: EX012 — Copenhagen Plank | G10: High | H10: EX001 — Back Squat (Barbell) | J10: High | K10: EX006 — Pull-Up (BW) | M10: Critical | N10: EX109 — Scapular Pull-Up | P10: Critical | Q10: EX121 — Trekking Pole Technique (Descent Braking) | S10: High | T10: EX080 — Lat Pulldown (Wide Grip) | V10: High | W10: EX043 — Single-Leg Balance Hold | Y10: High | Z10: EX021 — Bulgarian Split Squat (DB) | AA10: Critical | AB10: EX069 — Neck Extension Strengthening | AD10: High | AE10: EX151 — Rope Team Travel Drill | AG10: High | AH10: EX119 — Weighted Step-Up (High Box, Heavy Load) | AI10: Critical | AJ10: EX092 — Bracing Stroke Drill (High and Low) | AL10: Critical | AM10: EX166 — Ferry & Eddy Turn Technique | AO10: High | AP10: EX085 — Med Ball Rotational Throw (Wall) | AQ10: Critical | AR10: EX149 — Ice Axe Self-Arrest | AS10: Critical | AT10: EX082 — External Rotation (Band / Cable) | AU10: Critical | AV10: EX017 — Lateral Band Walk | AX10: Critical | AY10: EX025 — Single-Leg Calf Raise (Loaded) | AZ10: Critical | BA10: EX076 — Couch Stretch (Cyclist Hip Flexor) | BC10: Critical | BD10: EX069 — Neck Extension Strengthening | BF10: Critical | BG10: EX069 — Neck Extension Strengthening | BH10: High | BI10: EX022 — Reverse Lunge (DB or BW) | BK10: High | BL10: EX080 — Lat Pulldown (Wide Grip) | BN10: Critical | BO10: EX127 — Band Swimming Shoulder Prehab (Y-T-W-L) | BP10: Critical | BQ10: EX076 — Couch Stretch (Cyclist Hip Flexor) | BS10: Critical | BT10: EX082 — External Rotation (Band / Cable) | BU10: Critical | BV10: EX082 — External Rotation (Band / Cable) | BX10: Critical | BY10: EX207 — Double Pole Technique (XC Skiing) | CA10: High | CB10: EX085 — Med Ball Rotational Throw (Wall) | CC10: Critical | CD10: EX163 — Canoe Portage Yoke Carry | CF10: Critical | CG10: EX182 — Night Running & Low-Light Technique | CI10: High | CJ10: EX048 — Hill Repeats | CK10: Critical | CL10: EX021 — Bulgarian Split Squat (DB) | CN10: Critical | CO10: EX043 — Single-Leg Balance Hold | CP10: Critical | CQ10: EX230 — Conventional Deadlift (Barbell)
A11: High | B11: EX002 — Goblet Squat (DB/KB) | D11: High | E11: EX017 — Lateral Band Walk | G11: High | H11: EX002 — Goblet Squat (DB/KB) | J11: High | K11: EX078 — Single-Arm DB Row | M11: Critical | N11: EX110 — Antagonist Push-Up (Fist / Flat) | P11: Critical | Q11: EX123 — Pack Fit Optimization Drill | S11: High | T11: EX078 — Single-Arm DB Row | V11: High | W11: EX102 — Pinch Grip (Plate / Block) | Y11: High | Z11: EX024 — Step-Up High Box (Loaded) | AA11: Critical | AB11: EX076 — Couch Stretch (Cyclist Hip Flexor) | AD11: High | AE11: EX152 — Post-Hole Recovery Gait | AG11: High | AH11: EX017 — Lateral Band Walk | AI11: Critical | AJ11: EX093 — Eskimo Roll Practice | AL11: Critical | AM11: EX090 — Paddling Ergometer Session | AO11: High | AP11: EX087 — Cable High-to-Low Chop | AQ11: Critical | AR11: EX048 — Hill Repeats | AS11: Critical | AT11: EX073 — Threshold Intervals (Bike) | AU11: Critical | AV11: EX046 — Hip Flexor Lunge Stretch | AX11: Critical | AY11: EX117 — Loaded Step-Down (Eccentric Box) | AZ11: High | BA11: EX186 — High Cadence Spin Drill | BC11: Critical | BD11: EX068 — Wrist Pronation / Supination (DB) | BF11: Critical | BG11: EX076 — Couch Stretch (Cyclist Hip Flexor) | BH11: High | BI11: EX038 — Split Squat ISO Hold | BK11: High | BL11: EX089 — Hollow Body Hold | BN11: Critical | BO11: EX082 — External Rotation (Band / Cable) | BP11: Critical | BQ11: EX046 — Hip Flexor Lunge Stretch | BS11: Critical | BT11: EX043 — Single-Leg Balance Hold | BU11: Critical | BV11: EX047 — Calf / Achilles Wall Stretch | BX11: Critical | BY11: EX048 — Hill Repeats | CA11: High | CB11: EX086 — Landmine Rotation | CC11: Critical | CD11: EX082 — External Rotation (Band / Cable) | CF11: Critical | CG11: EX181 — On-the-Run Fueling Drill | CI11: High | CJ11: EX049 — Strides (Flying Sprints) | CK11: Critical | CL11: EX117 — Loaded Step-Down (Eccentric Box) | CN11: Critical | CO11: EX035 — Ankle Hops / Pogo Jumps | CP11: Critical | CQ11: EX243 — Suitcase Carry
A12: High | B12: EX003 — Romanian Deadlift (Barbell) | D12: High | E12: EX034 — Lateral Bound | G12: High | H12: EX019 — Barbell Hip Thrust | J12: High | K12: EX079 — Seated Cable Row (Narrow Grip) | M12: Critical | N12: EX112 — Belay Simulation (Device Practice) | P12: Critical | Q12: EX124 — Power Hiking Technique | S12: High | T12: EX081 — Band Face Pull | V12: High | W12: EX106 — Lock-Off Hold (90°, 120°) | Y12: High | Z12: EX043 — Single-Leg Balance Hold | AA12: High | AB12: EX147 — Loose Surface Threshold Braking | AD12: High | AE12: EX024 — Step-Up High Box (Loaded) | AG12: High | AH12: EX023 — Lateral Lunge (DB or BW) | AI12: Critical | AJ12: EX016 — Thoracic Rotation Drill | AL12: Critical | AM12: EX091 — Forward Stroke Technique Drill | AO12: High | AP12: EX078 — Single-Arm DB Row | AQ12: Critical | AR12: EX021 — Bulgarian Split Squat (DB) | AS12: Critical | AT12: EX075 — Sweet Spot Training (Bike) | AU12: Critical | AV12: EX047 — Calf / Achilles Wall Stretch | AX12: Critical | AY12: EX120 — Sustained LISS (Hiking Pace) | AZ12: High | BA12: EX074 — VO2 Max Intervals (Bike) | BC12: High | BD12: EX184 — Road Cycling Descending Technique | BF12: Critical | BG12: EX046 — Hip Flexor Lunge Stretch | BH12: High | BI12: EX023 — Lateral Lunge (DB or BW) | BK12: High | BL12: EX110 — Antagonist Push-Up (Fist / Flat) | BN12: Critical | BO12: EX178 — Tempo Run (Flat / Road) | BP12: High | BQ12: EX176 — Triathlon Transition Practice (T1 & T2) | BS12: High | BT12: EX142 — Bilateral Breathing Drill | BU12: Critical | BV12: EX045 — Ankle Mobility Drill (Wall) | BX12: High | BY12: EX208 — Herringbone & Steep Uphill Technique | CA12: High | CB12: EX089 — Hollow Body Hold | CC12: Critical | CD12: EX081 — Band Face Pull | CF12: Critical | CG12: EX124 — Power Hiking Technique | CI12: High | CJ12: EX025 — Single-Leg Calf Raise (Loaded) | CK12: Critical | CL12: EX020 — Nordic Hamstring Curl | CN12: Critical | CO12: EX027 — Tibialis Raise (Wall or Machine) | CP12: High | CQ12: EX221 — Mountain Climber
A13: High | B13: EX004 — Single-Leg RDL (DB) | D13: High | E13: EX048 — Hill Repeats | G13: High | H13: EX031 — Kettlebell Swing (Two-Hand) | J13: High | K13: EX080 — Lat Pulldown (Wide Grip) | M13: Critical | N13: EX113 — Movement on Route (Top-Rope / Lead) | P13: High | Q13: EX001 — Back Squat (Barbell) | S13: High | T13: EX083 — Serratus Punch | V13: High | W13: EX112 — Belay Simulation (Device Practice) | Y13: High | Z13: EX106 — Lock-Off Hold (90°, 120°) | AA13: High | AB13: EX074 — VO2 Max Intervals (Bike) | AD13: High | AE13: EX021 — Bulgarian Split Squat (DB) | AG13: High | AH13: EX040 — Clamshell (Band) | AI13: High | AJ13: EX156 — Sweep Stroke Technique Drill | AL13: Critical | AM13: EX087 — Cable High-to-Low Chop | AO13: High | AP13: EX089 — Hollow Body Hold | AQ13: Critical | AR13: EX017 — Lateral Band Walk | AS13: Critical | AT13: EX076 — Couch Stretch (Cyclist Hip Flexor) | AU13: Critical | AV13: EX018 — Foam Roll (IT Band / Quads / Lats) | AX13: Critical | AY13: EX124 — Power Hiking Technique | AZ13: High | BA13: EX070 — Single-Leg Cycling Drill (Trainer) | BC13: High | BD13: EX186 — High Cadence Spin Drill | BF13: High | BG13: EX186 — High Cadence Spin Drill | BH13: High | BI13: EX037 — Wall Sit | BK13: High | BL13: EX104 — Rice Bucket Drill | BN13: Critical | BO13: EX021 — Bulgarian Split Squat (DB) | BP13: High | BQ13: EX074 — VO2 Max Intervals (Bike) | BS13: High | BT13: EX081 — Band Face Pull | BU13: High | BV13: EX202 — Blade Extraction & Feathering Drill | BX13: High | BY13: EX021 — Bulgarian Split Squat (DB) | CA13: High | CB13: EX011 — Pallof Press (Band/Cable) | CC13: Critical | CD13: EX016 — Thoracic Rotation Drill | CF13: Critical | CG13: EX123 — Pack Fit Optimization Drill | CI13: High | CJ13: EX017 — Lateral Band Walk | CK13: Critical | CL13: EX033 — Depth Drop (Eccentric Landing Practice) | CN13: Critical | CO13: EX048 — Hill Repeats | CP13: High | CQ13: EX222 — Ab Wheel Rollout
A14: High | B14: EX007 — Box Jump | D14: High | E14: EX014 — World's Greatest Stretch | G14: High | H14: EX060 — Single-Leg Press (Machine) | J14: High | K14: EX083 — Serratus Punch | M14: Critical | N14: EX089 — Hollow Body Hold | P14: High | Q14: EX003 — Romanian Deadlift (Barbell) | S14: High | T14: EX016 — Thoracic Rotation Drill | V14: Medium | W14: EX009 — Farmer Carry | Y14: Medium | Z14: EX009 — Farmer Carry | AA14: High | AB14: EX019 — Barbell Hip Thrust | AD14: High | AE14: EX001 — Back Squat (Barbell) | AG14: High | AH14: EX041 — Monster Walk (Band) | AI14: High | AJ14: EX157 — Draw Stroke & Pry Technique | AL14: Critical | AM14: EX078 — Single-Arm DB Row | AO14: High | AP14: EX082 — External Rotation (Band / Cable) | AQ14: Critical | AR14: EX046 — Hip Flexor Lunge Stretch | AS14: Critical | AT14: EX016 — Thoracic Rotation Drill | AU14: High | AV14: EX026 — Seated Calf Raise | AX14: Critical | AY14: EX017 — Lateral Band Walk | AZ14: High | BA14: EX019 — Barbell Hip Thrust | BC14: High | BD14: EX189 — Road & Gravel Paceline Technique | BF14: High | BG14: EX187 — Gravel Surface Reading & Line Selection | BH14: High | BI14: EX025 — Single-Leg Calf Raise (Loaded) | BK14: High | BL14: EX102 — Pinch Grip (Plate / Block) | BN14: Critical | BO14: EX046 — Hip Flexor Lunge Stretch | BP14: High | BQ14: EX070 — Single-Leg Cycling Drill (Trainer) | BS14: High | BT14: EX016 — Thoracic Rotation Drill | BU14: High | BV14: EX006 — Pull-Up (BW) | BX14: High | BY14: EX040 — Clamshell (Band) | CA14: High | CB14: EX043 — Single-Leg Balance Hold | CC14: Critical | CD14: EX005 — Dead Hang | CF14: Critical | CG14: EX021 — Bulgarian Split Squat (DB) | CI14: High | CJ14: EX073 — Threshold Intervals (Bike) | CK14: Critical | CL14: EX043 — Single-Leg Balance Hold | CN14: Critical | CO14: EX051 — Uphill Running Technique Drill | CP14: High | CQ14: EX223 — Hanging Knee Raise / Toes-to-Bar
... A16: High | B16: EX012 — Copenhagen Plank | D16: High | E16: EX054 — T-Drill / 5-10-5 Cone Drill | G16: High | H16: EX062 — Banded Hip Flexion (Standing) | J16: High | K16: EX086 — Landmine Rotation | M16: High | N16: EX103 — Wrist Roller | P16: High | Q16: EX019 — Barbell Hip Thrust | S16: High | T16: EX065 — Scapular Wall Slide | V16: Medium | W16: EX011 — Pallof Press (Band/Cable) | Y16: Medium | Z16: EX104 — Rice Bucket Drill | AA16: High | AB16: EX021 — Bulgarian Split Squat (DB) | AD16: High | AE16: EX025 — Single-Leg Calf Raise (Loaded) | AG16: High | AH16: EX048 — Hill Repeats | AI16: High | AJ16: EX167 — Ocean / Surf Zone Entry & Exit | AL16: Critical | AM16: EX082 — External Rotation (Band / Cable) | AO16: High | AP16: EX016 — Thoracic Rotation Drill | AQ16: High | AR16: EX150 — Rest Step Technique | AS16: Critical | AT16: EX046 — Hip Flexor Lunge Stretch | AU16: High | AV16: EX020 — Nordic Hamstring Curl | AX16: Critical | AY16: EX047 — Calf / Achilles Wall Stretch | AZ16: High | BA16: EX021 — Bulgarian Split Squat (DB) | BC16: High | BD16: EX074 — VO2 Max Intervals (Bike) | BF16: High | BG16: EX009 — Farmer Carry | BH16: High | BI16: EX001 — Back Squat (Barbell) | BK16: High | BL16: EX095 — Portage Carry Simulation | BN16: High | BO16: EX195 — Rope Climb | BP16: High | BQ16: EX179 — Marathon Pace Run | BS16: High | BT16: EX178 — Tempo Run (Flat / Road) | BU16: High | BV16: EX080 — Lat Pulldown (Wide Grip) | BX16: High | BY16: EX012 — Copenhagen Plank | CA16: High | CB16: EX082 — External Rotation (Band / Cable) | CC16: High | CD16: EX156 — Sweep Stroke Technique Drill | CF16: Critical | CG16: EX048 — Hill Repeats | CI16: High | CJ16: EX067 — MTB Attack Position Hold | CK16: Critical | CL16: EX124 — Power Hiking Technique | CN16: Critical | CO16: EX047 — Calf / Achilles Wall Stretch | CP16: High | CQ16: EX225 — V-Sit Hold
A17: High | B17: EX013 — Hip Circle (Band) | D17: High | E17: EX055 — Lateral Shuffle Sprint | G17: High | H17: EX063 — Terminal Knee Extension (TKE) | J17: High | K17: EX087 — Cable High-to-Low Chop | M17: High | N17: EX104 — Rice Bucket Drill | P17: High | Q17: EX020 — Nordic Hamstring Curl | S17: High | T17: EX096 — 90/90 Shoulder Stretch | V17: Medium | W17: EX089 — Hollow Body Hold | AA17: High | AB17: EX062 — Banded Hip Flexion (Standing) | AD17: High | AE17: EX048 — Hill Repeats | AG17: High | AH17: EX050 — Treadmill Incline Walk (Loaded Pack) | AI17: High | AJ17: EX078 — Single-Arm DB Row | AL17: Critical | AM17: EX163 — Canoe Portage Yoke Carry | AO17: High | AP17: EX043 — Single-Leg Balance Hold | AQ17: High | AR17: EX152 — Post-Hole Recovery Gait | AS17: High | AT17: EX177 — Open Water Mass Start Technique | AU17: High | AV17: EX003 — Romanian Deadlift (Barbell) | AX17: Critical | AY17: EX018 — Foam Roll (IT Band / Quads / Lats) | AZ17: High | BA17: EX060 — Single-Leg Press (Machine) | BC17: High | BD17: EX070 — Single-Leg Cycling Drill (Trainer) | BF17: High | BG17: EX010 — Rucking (Weighted Hike) | BH17: High | BI17: EX053 — Agility Ladder Drill | BK17: High | BL17: EX021 — Bulgarian Split Squat (DB) | BN17: High | BO17: EX196 — Obstacle Vault & Wall Traversal | BP17: High | BQ17: EX048 — Hill Repeats | BS17: High | BT17: EX048 — Hill Repeats | BU17: High | BV17: EX078 — Single-Arm DB Row | BX17: High | BY17: EX025 — Single-Leg Calf Raise (Loaded) | CA17: High | CB17: EX081 — Band Face Pull | CC17: High | CD17: EX158 — Whitewater Line Reading | CF17: Critical | CG17: EX052 — Downhill Running Technique Drill | CI17: High | CJ17: EX091 — Forward Stroke Technique Drill | CK17: Critical | CL17: EX047 — Calf / Achilles Wall Stretch | CN17: High | CO17: EX033 — Depth Drop (Eccentric Landing Practice) | CP17: High | CQ17: EX226 — L-Sit (Between Chairs / Parallettes)
A18: High | B18: EX014 — World's Greatest Stretch | D18: High | E18: EX059 — Neck Isometric Hold (Map Reading Position) | G18: High | H18: EX064 — Reverse Nordic Curl | J18: High | K18: EX089 — Hollow Body Hold | M18: High | N18: EX107 — One-Arm Assisted Hang | P18: High | Q18: EX025 — Single-Leg Calf Raise (Loaded) | S18: High | T18: EX084 — Scapular Depression Hold | AA18: High | AB18: EX063 — Terminal Knee Extension (TKE) | AD18: High | AE18: EX050 — Treadmill Incline Walk (Loaded Pack) | AG18: High | AH18: EX046 — Hip Flexor Lunge Stretch | AI18: High | AJ18: EX079 — Seated Cable Row (Narrow Grip) | AL18: High | AM18: EX160 — Seated Paddling Position Endurance | AO18: High | AP18: EX095 — Portage Carry Simulation | AQ18: High | AR18: EX073 — Threshold Intervals (Bike) | AS18: High | AT18: EX128 — Kicking Drill (Flutter / Frog) | AU18: High | AV18: EX004 — Single-Leg RDL (DB) | AX18: Critical | AY18: EX048 — Hill Repeats | AZ18: High | BA18: EX061 — Good Morning (Barbell) | BC18: High | BD18: EX019 — Barbell Hip Thrust | BF18: High | BG18: EX095 — Portage Carry Simulation | BH18: High | BI18: EX055 — Lateral Shuffle Sprint | BK18: High | BL18: EX007 — Box Jump | BN18: High | BO18: EX006 — Pull-Up (BW) | BP18: High | BQ18: EX049 — Strides (Flying Sprints) | BS18: High | BT18: EX049 — Strides (Flying Sprints) | BU18: High | BV18: EX019 — Barbell Hip Thrust | BX18: High | BY18: EX026 — Seated Calf Raise | CA18: High | CB18: EX078 — Single-Arm DB Row | CC18: High | CD18: EX009 — Farmer Carry | CF18: High | CG18: EX056 — Reactive Direction Change Drill | CI18: High | CJ18: EX090 — Paddling Ergometer Session | CK18: Critical | CL18: EX018 — Foam Roll (IT Band / Quads / Lats) | CN18: High | CO18: EX044 — BOSU Single-Leg Squat | CP18: High | CQ18: EX227 — Compression Tuck Hold
A19: High | B19: EX015 — Pigeon Pose | D19: Medium | E19: EX001 — Back Squat (Barbell) | G19: High | H19: EX065 — Scapular Wall Slide | J19: High | K19: EX095 — Portage Carry Simulation | M19: High | N19: EX108 — Foot-On Campus Board Move | P19: High | Q19: EX026 — Seated Calf Raise | S19: Medium | T19: EX085 — Med Ball Rotational Throw (Wall) | AA19: High | AB19: EX067 — MTB Attack Position Hold | AD19: High | AE19: EX009 — Farmer Carry | AG19: High | AH19: EX124 — Power Hiking Technique | AI19: High | AJ19: EX080 — Lat Pulldown (Wide Grip) | AL19: High | AM19: EX088 — Russian Twist (DB / Med Ball) | AO19: High | AP19: EX009 — Farmer Carry | AQ19: High | AR19: EX075 — Sweet Spot Training (Bike) | AS19: High | AT19: EX129 — Swim-Specific Rotational Core (Dry Land) | AU19: High | AV19: EX019 — Barbell Hip Thrust | AX19: Critical | AY19: EX051 — Uphill Running Technique Drill | AZ19: High | BA19: EX062 — Banded Hip Flexion (Standing) | BC19: High | BD19: EX001 — Back Squat (Barbell) | BF19: High | BG19: EX019 — Barbell Hip Thrust | BH19: High | BI19: EX082 — External Rotation (Band / Cable) | BK19: High | BL19: EX008 — Broad Jump | BN19: High | BO19: EX005 — Dead Hang | BP19: High | BQ19: EX019 — Barbell Hip Thrust | BS19: High | BT19: EX025 — Single-Leg Calf Raise (Loaded) | BU19: High | BV19: EX003 — Romanian Deadlift (Barbell) | BX19: High | BY19: EX020 — Nordic Hamstring Curl | CA19: High | CB19: EX006 — Pull-Up (BW) | CC19: High | CD19: EX083 — Serratus Punch | CF19: High | CG19: EX183 — Running with Poles (Trail / Ultra) | CI19: High | CJ19: EX082 — External Rotation (Band / Cable) | CK19: High | CL19: EX028 — Pistol Squat / Assisted Pistol | CN19: High | CO19: EX034 — Lateral Bound | CP19: High | CQ19: EX229 — Bench Press (Barbell / DB)
A20: High | B20: EX017 — Lateral Band Walk | D20: Medium | E20: EX002 — Goblet Squat (DB/KB) | G20: High | H20: EX066 — Band Pull-Apart | J20: High | K20: EX011 — Pallof Press (Band/Cable) | M20: High | N20: EX111 — Reverse Wrist Curl (DB) | P20: High | Q20: EX027 — Tibialis Raise (Wall or Machine) | S20: Medium | T20: EX087 — Cable High-to-Low Chop | AA20: High | AB20: EX016 — Thoracic Rotation Drill | AD20: High | AE20: EX043 — Single-Leg Balance Hold | AG20: High | AH20: EX014 — World's Greatest Stretch | AI20: High | AJ20: EX087 — Cable High-to-Low Chop | AL20: High | AM20: EX086 — Landmine Rotation | AO20: High | AP20: EX092 — Bracing Stroke Drill (High and Low) | AQ20: High | AR20: EX010 — Rucking (Weighted Hike) | AS20: High | AT20: EX141 — Wetsuit Swimming Technique | AU20: High | AV20: EX001 — Back Squat (Barbell) | AX20: Critical | AY20: EX052 — Downhill Running Technique Drill | AZ20: High | BA20: EX063 — Terminal Knee Extension (TKE) | BC20: High | BD20: EX021 — Bulgarian Split Squat (DB) | BF20: High | BG20: EX001 — Back Squat (Barbell) | BH20: High | BI20: EX068 — Wrist Pronation / Supination (DB) | BK20: High | BL20: EX048 — Hill Repeats | BN20: High | BO20: EX016 — Thoracic Rotation Drill | BP20: High | BQ20: EX020 — Nordic Hamstring Curl | BS20: High | BT20: EX021 — Bulgarian Split Squat (DB) | BU20: High | BV20: EX011 — Pallof Press (Band/Cable) | BX20: High | BY20: EX098 — DB Shoulder Press | CA20: High | CB20: EX065 — Scapular Wall Slide | CC20: High | CD20: EX084 — Scapular Depression Hold | CF20: High | CG20: EX122 — Hip Hinge Under Pack (Practice Drill) | CI20: High | CJ20: EX016 — Thoracic Rotation Drill | CK20: High | CL20: EX034 — Lateral Bound | CN20: High | CO20: EX019 — Barbell Hip Thrust | CP20: High | CQ20: EX231 — Front Squat (Barbell / KB)
A21: High | B21: EX018 — Foam Roll (IT Band / Quads / Lats) | D21: Medium | E21: EX004 — Single-Leg RDL (DB) | G21: High | H21: EX068 — Wrist Pronation / Supination (DB) | J21: High | K21: EX081 — Band Face Pull | M21: High | N21: EX114 — Flagging / Hip Drop Technique Drill | P21: High | Q21: EX030 — Reverse Sled Drag | S21: Medium | T21: EX079 — Seated Cable Row (Narrow Grip) | AA21: High | AB21: EX065 — Scapular Wall Slide | AD21: High | AE21: EX044 — BOSU Single-Leg Squat | AG21: Medium | AH21: EX025 — Single-Leg Calf Raise (Loaded) | AI21: High | AJ21: EX085 — Med Ball Rotational Throw (Wall) | AL21: High | AM21: EX085 — Med Ball Rotational Throw (Wall) | AO21: High | AP21: EX166 — Ferry & Eddy Turn Technique | AQ21: High | AR21: EX050 — Treadmill Incline Walk (Loaded Pack) | AS21: High | AT21: EX142 — Bilateral Breathing Drill | AU21: High | AV21: EX023 — Lateral Lunge (DB or BW) | AX21: High | AY21: EX178 — Tempo Run (Flat / Road) | AZ21: High | BA21: EX064 — Reverse Nordic Curl | BC21: High | BD21: EX043 — Single-Leg Balance Hold | BF21: High | BG21: EX021 — Bulgarian Split Squat (DB) | BH21: High | BI21: EX111 — Reverse Wrist Curl (DB) | BK21: High | BL21: EX043 — Single-Leg Balance Hold | BN21: High | BO21: EX049 — Strides (Flying Sprints) | BP21: High | BQ21: EX001 — Back Squat (Barbell) | BS21: High | BT21: EX017 — Lateral Band Walk | BU21: High | BV21: EX085 — Med Ball Rotational Throw (Wall) | BX21: High | BY21: EX118 — Trekking Pole Push Drill | CA21: High | CB21: EX096 — 90/90 Shoulder Stretch | CC21: High | CD21: EX096 — 90/90 Shoulder Stretch | CF21: High | CG21: EX020 — Nordic Hamstring Curl | CI21: High | CJ21: EX052 — Downhill Running Technique Drill | CK21: High | CL21: EX035 — Ankle Hops / Pogo Jumps | CN21: High | CO21: EX036 — Running Bounds (Exaggerated Stride) | CP21: High | CQ21: EX232 — Hang Clean (Barbell / KB)
A22: High | B22: EX019 — Barbell Hip Thrust | D22: Medium | E22: EX007 — Box Jump | G22: High | H22: EX069 — Neck Extension Strengthening | J22: High | K22: EX084 — Scapular Depression Hold | M22: High | N22: EX115 — Foot Smear Strength (Incline Board) | P22: High | Q22: EX037 — Wall Sit | AA22: High | AB22: EX018 — Foam Roll (IT Band / Quads / Lats) | AD22: High | AE22: EX123 — Pack Fit Optimization Drill | AG22: Medium | AH22: EX123 — Pack Fit Optimization Drill | AI22: High | AJ22: EX086 — Landmine Rotation | AL22: High | AM22: EX079 — Seated Cable Row (Narrow Grip) | AO22: Medium | AP22: EX011 — Pallof Press (Band/Cable) | AQ22: High | AR22: EX120 — Sustained LISS (Hiking Pace) | AS22: High | AT22: EX081 — Band Face Pull | AU22: High | AV22: EX030 — Reverse Sled Drag | AX22: High | AY22: EX179 — Marathon Pace Run | AZ22: High | BA22: EX016 — Thoracic Rotation Drill | BC22: High | BD22: EX016 — Thoracic Rotation Drill | BF22: High | BG22: EX003 — Romanian Deadlift (Barbell) | BH22: High | BI22: EX023 — Lateral Lunge (DB or BW) | BK22: High | BL22: EX044 — BOSU Single-Leg Squat | BN22: High | BO22: EX048 — Hill Repeats | BP22: High | BQ22: EX025 — Single-Leg Calf Raise (Loaded) | BS22: High | BT22: EX044 — BOSU Single-Leg Squat | BU22: High | BV22: EX081 — Band Face Pull | BX22: High | BY22: EX086 — Landmine Rotation | CA22: High | CB22: EX025 — Single-Leg Calf Raise (Loaded) | CC22: High | CD22: EX065 — Scapular Wall Slide | CF22: High | CG22: EX025 — Single-Leg Calf Raise (Loaded) | CI22: High | CJ22: EX051 — Uphill Running Technique Drill | CK22: High | CL22: EX044 — BOSU Single-Leg Squat | CN22: High | CO22: EX057 — Map Navigation Run | CP22: High | CQ22: EX233 — Lateral Raise (DB / Band)
A23: High | B23: EX020 — Nordic Hamstring Curl | D23: Medium | E23: EX013 — Hip Circle (Band) | G23: High | H23: EX071 — Cornering Technique Drill | J23: High | K23: EX094 — Packraft Inflation / Deflation Drill | M23: High | N23: EX116 — Mantling Technique Drill | P23: High | Q23: EX009 — Farmer Carry | AA23: High | AB23: EX015 — Pigeon Pose | AD23: High | AE23: EX134 — Ascender / Jumar Technique Drill | AI23: High | AJ23: EX006 — Pull-Up (BW) | AL23: High | AM23: EX080 — Lat Pulldown (Wide Grip) | AQ23: High | AR23: EX001 — Back Squat (Barbell) | AS23: High | AT23: EX083 — Serratus Punch | AU23: High | AV23: EX036 — Running Bounds (Exaggerated Stride) | AX23: High | AY23: EX026 — Seated Calf Raise | AZ23: High | BA23: EX065 — Scapular Wall Slide | BC23: High | BD23: EX018 — Foam Roll (IT Band / Quads / Lats) | BF23: High | BG23: EX061 — Good Morning (Barbell) | BH23: High | BI23: EX015 — Pigeon Pose | BK23: High | BL23: EX178 — Tempo Run (Flat / Road) | BN23: High | BO23: EX019 — Barbell Hip Thrust | BP23: High | BQ23: EX026 — Seated Calf Raise | BS23: High | BT23: EX143 — Water & Stream Crossing Technique | BU23: High | BV23: EX066 — Band Pull-Apart | BX23: High | BY23: EX073 — Threshold Intervals (Bike) | CA23: High | CB23: EX023 — Lateral Lunge (DB or BW) | CC23: High | CD23: EX006 — Pull-Up (BW) | CF23: High | CG23: EX051 — Uphill Running Technique Drill | CI23: High | CJ23: EX071 — Cornering Technique Drill (MTB) | CK23: High | CL23: EX019 — Barbell Hip Thrust | CN23: High | CO23: EX058 — Compass Bearing Walk / Run | CP23: High | CQ23: EX234 — Hammer Curl (DB)
A24: High | B24: EX022 — Reverse Lunge (DB or BW) | D24: Medium | E24: EX019 — Barbell Hip Thrust | G24: High | H24: EX072 — Pump Track / Trail Feature Technique | J24: High | K24: EX096 — 90/90 Shoulder Stretch | M24: High | N24: EX023 — Lateral Lunge (DB or BW) | P24: High | Q24: EX050 — Treadmill Incline Walk (Loaded Pack) | AA24: High | AB24: EX077 — Doorway Pec Stretch | AD24: High | AE24: EX136 — Fixed Rope Body Position & Rest Drill | AI24: High | AJ24: EX089 — Hollow Body Hold | AL24: High | AM24: EX006 — Pull-Up (BW) | AQ24: High | AR24: EX023 — Lateral Lunge (DB or BW) | AS24: High | AT24: EX084 — Scapular Depression Hold | AU24: High | AV24: EX049 — Strides (Flying Sprints) | AX24: High | AY24: EX027 — Tibialis Raise (Wall or Machine) | AZ24: High | BA24: EX066 — Band Pull-Apart | BC24: High | BD24: EX015 — Pigeon Pose | BF24: High | BG24: EX016 — Thoracic Rotation Drill | BH24: High | BI24: EX014 — World's Greatest Stretch | BK24: High | BL24: EX049 — Strides (Flying Sprints) | BN24: High | BO24: EX001 — Back Squat (Barbell) | BP24: High | BQ24: EX063 — Terminal Knee Extension (TKE) | BS24: High | BT24: EX046 — Hip Flexor Lunge Stretch | BU24: High | BV24: EX109 — Scapular Pull-Up | BX24: High | BY24: EX075 — Sweet Spot Training (Bike) | CA24: High | CB24: EX018 — Foam Roll (IT Band / Quads / Lats) | CC24: High | CD24: EX078 — Single-Arm DB Row | CF24: High | CG24: EX143 — Water & Stream Crossing Technique | CI24: High | CJ24: EX019 — Barbell Hip Thrust | CK24: High | CL24: EX036 — Running Bounds (Exaggerated Stride) | CN24: High | CO24: EX001 — Back Squat (Barbell) | CP24: High | CQ24: EX235 — Tricep Pushdown / Extension (Cable / Band)
A25: High | B25: EX023 — Lateral Lunge (DB or BW) | D25: Medium | E25: EX021 — Bulgarian Split Squat (DB) | G25: High | H25: EX014 — World's Greatest Stretch | J25: High | K25: EX097 — Pec Minor Stretch (Low Doorway) | M25: High | N25: EX028 — Pistol Squat / Assisted Pistol | P25: High | Q25: EX118 — Trekking Pole Push Drill | AA25: High | AB25: EX031 — Kettlebell Swing (Two-Hand) | AD25: High | AE25: EX015 — Pigeon Pose | AI25: High | AJ25: EX011 — Pallof Press (Band/Cable) | AL25: High | AM25: EX089 — Hollow Body Hold | AQ25: High | AR25: EX012 — Copenhagen Plank | AS25: High | AT25: EX096 — 90/90 Shoulder Stretch | AU25: High | AV25: EX039 — Glute Bridge (Double-Leg) | AX25: High | AY25: EX019 — Barbell Hip Thrust | AZ25: High | BA25: EX077 — Doorway Pec Stretch | BF25: High | BG25: EX015 — Pigeon Pose | BH25: Medium | BI25: EX098 — DB Shoulder Press | BK25: High | BL25: EX014 — World's Greatest Stretch | BN25: High | BO25: EX009 — Farmer Carry | BP25: High | BQ25: EX039 — Glute Bridge (Double-Leg) | BS25: High | BT25: EX047 — Calf / Achilles Wall Stretch | BU25: High | BV25: EX065 — Scapular Wall Slide | BX25: High | BY25: EX046 — Hip Flexor Lunge Stretch | CA25: High | CB25: EX159 — Wet Exit & Re-entry (Kayak) | CC25: High | CD25: EX080 — Lat Pulldown (Wide Grip) | CF25: High | CG25: EX014 — World's Greatest Stretch | CI25: High | CJ25: EX020 — Nordic Hamstring Curl | CK25: High | CL25: EX183 — Running with Poles (Trail / Ultra) | CN25: High | CO25: EX028 — Pistol Squat / Assisted Pistol | CP25: High | CQ25: EX236 — Leg Curl (Machine / Band)
A26: High | B26: EX024 — Step-Up High Box (Loaded) | D26: Medium | E26: EX039 — Glute Bridge (Double-Leg) | G26: High | H26: EX015 — Pigeon Pose | J26: High | K26: EX099 — External Rotation to Press (Band / Cable) | M26: High | N26: EX016 — Thoracic Rotation Drill | P26: High | Q26: EX122 — Hip Hinge Under Pack (Practice Drill) | AA26: Medium | AB26: EX009 — Farmer Carry | AD26: High | AE26: EX046 — Hip Flexor Lunge Stretch | AI26: High | AJ26: EX081 — Band Face Pull | AL26: High | AM26: EX011 — Pallof Press (Band/Cable) | AQ26: High | AR26: EX019 — Barbell Hip Thrust | AS26: High | AT26: EX074 — VO2 Max Intervals (Bike) | AU26: High | AV26: EX040 — Clamshell (Band) | AX26: High | AY26: EX003 — Romanian Deadlift (Barbell) | AZ26: High | BA26: EX015 — Pigeon Pose | BF26: High | BG26: EX047 — Calf / Achilles Wall Stretch | BH26: Low | BI26: EX193 — Shooting Breath Control & Stance | BK26: High | BL26: EX018 — Foam Roll (IT Band / Quads / Lats) | BN26: High | BO26: EX014 — World's Greatest Stretch | BP26: High | BQ26: EX016 — Thoracic Rotation Drill | BS26: High | BT26: EX014 — World's Greatest Stretch | BU26: High | BV26: EX096 — 90/90 Shoulder Stretch | BX26: High | BY26: EX076 — Couch Stretch (Cyclist Hip Flexor) | CA26: Medium | CB26: EX140 — Open Water Sighting Drill | CC26: High | CD26: EX087 — Cable High-to-Low Chop | CF26: High | CG26: EX046 — Hip Flexor Lunge Stretch | CI26: High | CJ26: EX014 — World's Greatest Stretch | CK26: High | CL26: EX009 — Farmer Carry | CN26: High | CO26: EX012 — Copenhagen Plank | CP26: High | CQ26: EX238 — Burpee
A27: High | B27: EX026 — Seated Calf Raise | D27: Medium | E27: EX040 — Clamshell (Band) | G27: High | H27: EX016 — Thoracic Rotation Drill | J27: Medium | K27: EX009 — Farmer Carry | M27: High | N27: EX045 — Ankle Mobility Drill (Wall) | P27: High | Q27: EX125 — Quad-Eccentric Walk (Controlled Descent) | AA27: Medium | AB27: EX066 — Band Pull-Apart | AD27: High | AE27: EX014 — World's Greatest Stretch | AI27: High | AJ27: EX083 — Serratus Punch | AL27: High | AM27: EX081 — Band Face Pull | AQ27: High | AR27: EX020 — Nordic Hamstring Curl | AS27: High | AT27: EX070 — Single-Leg Cycling Drill (Trainer) | AU27: High | AV27: EX013 — Hip Circle (Band) | AX27: High | AY27: EX004 — Single-Leg RDL (DB) | AZ27: High | BA27: EX018 — Foam Roll (IT Band / Quads / Lats) | BF27: High | BG27: EX018 — Foam Roll (IT Band / Quads / Lats) | BK27: Medium | BL27: EX034 — Lateral Bound | BN27: Medium | BO27: EX140 — Open Water Sighting Drill | BP27: High | BQ27: EX015 — Pigeon Pose | BS27: High | BT27: EX018 — Foam Roll (IT Band / Quads / Lats) | BU27: High | BV27: EX016 — Thoracic Rotation Drill | BX27: High | BY27: EX016 — Thoracic Rotation Drill | CC27: High | CD27: EX089 — Hollow Body Hold | CF27: High | CG27: EX047 — Calf / Achilles Wall Stretch | CI27: High | CJ27: EX046 — Hip Flexor Lunge Stretch | CK27: High | CL27: EX181 — On-the-Run Fueling Drill | CN27: High | CO27: EX030 — Reverse Sled Drag | CP27: High | CQ27: EX239 — Turkish Get-Up (KB / DB)
A28: High | B28: EX027 — Tibialis Raise (Wall or Machine) | D28: Medium | E28: EX041 — Monster Walk (Band) | G28: High | H28: EX018 — Foam Roll (IT Band / Quads / Lats) | J28: Medium | K28: EX014 — World's Greatest Stretch | M28: High | N28: EX043 — Single-Leg Balance Hold | P28: High | Q28: EX013 — Hip Circle (Band) | AD28: High | AE28: EX018 — Foam Roll (IT Band / Quads / Lats) | AI28: High | AJ28: EX084 — Scapular Depression Hold | AL28: High | AM28: EX083 — Serratus Punch | AQ28: High | AR28: EX037 — Wall Sit | AS28: High | AT28: EX065 — Scapular Wall Slide | AU28: High | AV28: EX041 — Monster Walk (Band) | AX28: High | AY28: EX028 — Pistol Squat / Assisted Pistol | AZ28: High | BA28: EX068 — Wrist Pronation / Supination (DB) | BF28: High | BG28: EX068 — Wrist Pronation / Supination (DB) | BP28: High | BQ28: EX017 — Lateral Band Walk | BU28: High | BV28: EX046 — Hip Flexor Lunge Stretch | BX28: High | BY28: EX047 — Calf / Achilles Wall Stretch | CC28: High | CD28: EX011 — Pallof Press (Band/Cable) | CF28: High | CG28: EX043 — Single-Leg Balance Hold | CI28: High | CJ28: EX039 — Glute Bridge (Double-Leg) | CK28: High | CL28: EX182 — Night Running & Low-Light Technique | CN28: High | CO28: EX046 — Hip Flexor Lunge Stretch | CP28: High | CQ28: EX240 — Bear Crawl
A29: High | B29: EX028 — Pistol Squat / Assisted Pistol | D29: Medium | E29: EX049 — Strides (Flying Sprints) | G29: High | H29: EX077 — Doorway Pec Stretch | J29: Medium | K29: EX015 — Pigeon Pose | M29: High | N29: EX011 — Pallof Press (Band/Cable) | P29: High | Q29: EX015 — Pigeon Pose | AD29: Medium | AE29: EX143 — Water & Stream Crossing Technique | AI29: High | AJ29: EX096 — 90/90 Shoulder Stretch | AL29: High | AM29: EX096 — 90/90 Shoulder Stretch | AQ29: High | AR29: EX025 — Single-Leg Calf Raise (Loaded) | AS29: High | AT29: EX066 — Band Pull-Apart | AU29: High | AV29: EX063 — Terminal Knee Extension (TKE) | AX29: High | AY29: EX030 — Reverse Sled Drag | AZ29: Medium | BA29: EX020 — Nordic Hamstring Curl | BF29: High | BG29: EX123 — Pack Fit Optimization Drill | BP29: High | BQ29: EX047 — Calf / Achilles Wall Stretch | BU29: High | BV29: EX018 — Foam Roll (IT Band / Quads / Lats) | BX29: High | BY29: EX014 — World's Greatest Stretch | CC29: High | CD29: EX018 — Foam Roll (IT Band / Quads / Lats) | CF29: High | CG29: EX018 — Foam Roll (IT Band / Quads / Lats) | CI29: High | CJ29: EX013 — Hip Circle (Band) | CK29: High | CL29: EX046 — Hip Flexor Lunge Stretch | CN29: High | CO29: EX018 — Foam Roll (IT Band / Quads / Lats) | CP29: High | CQ29: EX241 — Single-Arm KB Front Squat
A30: High | B30: EX030 — Reverse Sled Drag | D30: Low | E30: EX050 — Treadmill Incline Walk (Loaded Pack) | G30: Medium | H30: EX020 — Nordic Hamstring Curl | J30: Medium | K30: EX088 — Russian Twist (DB / Med Ball) | M30: High | N30: EX096 — 90/90 Shoulder Stretch | P30: High | Q30: EX046 — Hip Flexor Lunge Stretch | AD30: Medium | AE30: EX089 — Hollow Body Hold | AI30: High | AJ30: EX095 — Portage Carry Simulation | AL30: High | AM30: EX095 — Portage Carry Simulation | AQ30: High | AR30: EX030 — Reverse Sled Drag | AS30: High | AT30: EX062 — Banded Hip Flexion (Standing) | AU30: High | AV30: EX014 — World's Greatest Stretch | AX30: High | AY30: EX010 — Rucking (Weighted Hike) | AZ30: Medium | BA30: EX067 — MTB Attack Position Hold | BF30: High | BG30: EX014 — World's Greatest Stretch | BP30: High | BQ30: EX018 — Foam Roll (IT Band / Quads / Lats) | BU30: High | BV30: EX076 — Couch Stretch (Cyclist Hip Flexor) | BX30: High | BY30: EX018 — Foam Roll (IT Band / Quads / Lats) | CC30: High | CD30: EX015 — Pigeon Pose | CI30: High | CJ30: EX018 — Foam Roll (IT Band / Quads / Lats) | CK30: High | CL30: EX014 — World's Greatest Stretch | CN30: High | CO30: EX015 — Pigeon Pose | CP30: High | CQ30: EX242 — Single-Arm DB Bench Press
A31: High | B31: EX031 — Kettlebell Swing (Two-Hand) | G31: Medium | H31: EX003 — Romanian Deadlift (Barbell) | J31: Medium | K31: EX093 — Eskimo Roll Practice | M31: Medium | N31: EX019 — Barbell Hip Thrust | P31: High | Q31: EX047 — Calf / Achilles Wall Stretch | AI31: Medium | AJ31: EX088 — Russian Twist (DB / Med Ball) | AL31: Medium | AM31: EX009 — Farmer Carry | AQ31: High | AR31: EX040 — Clamshell (Band) | AS31: High | AT31: EX063 — Terminal Knee Extension (TKE) | AU31: High | AV31: EX045 — Ankle Mobility Drill (Wall) | AX31: High | AY31: EX035 — Ankle Hops / Pogo Jumps | BF31: Medium | BG31: EX189 — Road & Gravel Paceline Technique | BP31: High | BQ31: EX014 — World's Greatest Stretch | BU31: High | BV31: EX015 — Pigeon Pose | BX31: High | BY31: EX120 — Sustained LISS (Hiking Pace) | CK31: High | CL31: EX015 — Pigeon Pose | CN31: High | CO31: EX014 — World's Greatest Stretch | CP31: High | CQ31: EX244 — Overhead Carry / Waiter Walk
A32: High | B32: EX033 — Depth Drop (Eccentric Landing Practice) | G32: Medium | H32: EX007 — Box Jump | J32: Medium | K32: EX098 — DB Shoulder Press | M32: Medium | N32: EX012 — Copenhagen Plank | P32: High | Q32: EX014 — World's Greatest Stretch | AI32: Medium | AJ32: EX065 — Scapular Wall Slide | AQ32: High | AR32: EX041 — Monster Walk (Band) | AS32: High | AT32: EX077 — Doorway Pec Stretch | AU32: High | AV32: EX015 — Pigeon Pose | AX32: High | AY32: EX034 — Lateral Bound | BP32: Medium | BQ32: EX027 — Tibialis Raise (Wall or Machine) | BU32: Medium | BV32: EX021 — Bulgarian Split Squat (DB) | CK32: High | CL32: EX045 — Ankle Mobility Drill (Wall) | CN32: High | CO32: EX024 — Step-Up High Box (Loaded) | CP32: High | CQ32: EX245 — Single-Arm KB Clean
A33: High | B33: EX034 — Lateral Bound | G33: Medium | H33: EX011 — Pallof Press (Band/Cable) | J33: Medium | K33: EX065 — Scapular Wall Slide | M33: Medium | N33: EX009 — Farmer Carry | P33: High | Q33: EX018 — Foam Roll (IT Band / Quads / Lats) | AI33: Medium | AJ33: EX009 — Farmer Carry | AQ33: High | AR33: EX043 — Single-Leg Balance Hold | AS33: High | AT33: EX019 — Barbell Hip Thrust | AU33: High | AV33: EX048 — Hill Repeats | AX33: High | AY33: EX033 — Depth Drop (Eccentric Landing Practice) | BU33: Medium | BV33: EX087 — Cable High-to-Low Chop | CK33: Medium | CL33: EX016 — Thoracic Rotation Drill | CP33: Medium | CQ33: EX237 — Leg Extension (Machine)
A34: High | B34: EX035 — Ankle Hops / Pogo Jumps | G34: Medium | H34: EX013 — Hip Circle (Band) | J34: Medium | K34: EX066 — Band Pull-Apart | P34: High | Q34: EX043 — Single-Leg Balance Hold | AQ34: High | AR34: EX044 — BOSU Single-Leg Squat | AS34: High | AT34: EX001 — Back Squat (Barbell) | AU34: High | AV34: EX052 — Downhill Running Technique Drill | AX34: High | AY34: EX039 — Glute Bridge (Double-Leg) | BU34: Medium | BV34: EX048 — Hill Repeats
A35: High | B35: EX036 — Running Bounds (Exaggerated Stride) | G35: Medium | H35: EX021 — Bulgarian Split Squat (DB) | P35: Medium | Q35: EX029 — Sled Push | AQ35: High | AR35: EX014 — World's Greatest Stretch | AS35: High | AT35: EX021 — Bulgarian Split Squat (DB) | AU35: Medium | AV35: EX028 — Pistol Squat / Assisted Pistol | AX35: High | AY35: EX040 — Clamshell (Band) | BU35: Medium | BV35: EX120 — Sustained LISS (Hiking Pace)
A36: High | B36: EX038 — Split Squat ISO Hold | G36: Medium | H36: EX032 — Jump Squat (BW or Light Load) | P36: Medium | Q36: EX048 — Hill Repeats | AQ36: High | AR36: EX076 — Couch Stretch (Cyclist Hip Flexor) | AS36: High | AT36: EX018 — Foam Roll (IT Band / Quads / Lats) | AU36: Medium | AV36: EX007 — Box Jump | AX36: High | AY36: EX013 — Hip Circle (Band)
A37: High | B37: EX039 — Glute Bridge (Double-Leg) | G37: Medium | H37: EX037 — Wall Sit | P37: Medium | Q37: EX011 — Pallof Press (Band/Cable) | AQ37: High | AR37: EX015 — Pigeon Pose | AS37: High | AT37: EX048 — Hill Repeats | AU37: Medium | AV37: EX008 — Broad Jump | AX37: High | AY37: EX015 — Pigeon Pose
A38: High | B38: EX040 — Clamshell (Band) | G38: Low | H38: EX009 — Farmer Carry | AQ38: High | AR38: EX047 — Calf / Achilles Wall Stretch | AS38: High | AT38: EX049 — Strides (Flying Sprints) | AU38: Medium | AV38: EX016 — Thoracic Rotation Drill | AX38: High | AY38: EX045 — Ankle Mobility Drill (Wall)
A39: High | B39: EX041 — Monster Walk (Band) | AQ39: High | AR39: EX018 — Foam Roll (IT Band / Quads / Lats) | AS39: High | AT39: EX025 — Single-Leg Calf Raise (Loaded) | AU39: Medium | AV39: EX051 — Uphill Running Technique Drill | AX39: High | AY39: EX014 — World's Greatest Stretch
A40: High | B40: EX043 — Single-Leg Balance Hold | AQ40: High | AR40: EX124 — Power Hiking Technique | AS40: High | AT40: EX026 — Seated Calf Raise | AX40: High | AY40: EX143 — Water & Stream Crossing Technique
A41: High | B41: EX044 — BOSU Single-Leg Squat | AQ41: High | AR41: EX123 — Pack Fit Optimization Drill | AS41: High | AT41: EX027 — Tibialis Raise (Wall or Machine) | AX41: Medium | AY41: EX049 — Strides (Flying Sprints)
A42: High | B42: EX045 — Ankle Mobility Drill (Wall) | AS42: High | AT42: EX020 — Nordic Hamstring Curl
A43: High | B43: EX046 — Hip Flexor Lunge Stretch | AS43: High | AT43: EX003 — Romanian Deadlift (Barbell)
A44: High | B44: EX047 — Calf / Achilles Wall Stretch | AS44: High | AT44: EX004 — Single-Leg RDL (DB)
A45: High | B45: EX049 — Strides (Flying Sprints) | AS45: High | AT45: EX035 — Ankle Hops / Pogo Jumps
A46: High | B46: EX050 — Treadmill Incline Walk (Loaded Pack) | AS46: High | AT46: EX047 — Calf / Achilles Wall Stretch
A47: Medium | B47: EX009 — Farmer Carry | AS47: High | AT47: EX015 — Pigeon Pose
A48: Medium | B48: EX011 — Pallof Press (Band/Cable) | AS48: High | AT48: EX014 — World's Greatest Stretch
A49: Medium | B49: EX016 — Thoracic Rotation Drill | AS49: High | AT49: EX039 — Glute Bridge (Double-Leg)
A50: Medium | B50: EX029 — Sled Push | AS50: High | AT50: EX017 — Lateral Band Walk
A51: Medium | B51: EX032 — Jump Squat (BW or Light Load) | AS51: High | AT51: EX013 — Hip Circle (Band)
A52: Medium | B52: EX037 — Wall Sit | AS52: Medium | AT52: EX006 — Pull-Up (BW)
A53: Medium | B53: EX042 — Donkey Kick / Fire Hydrant | AS53: Medium | AT53: EX080 — Lat Pulldown (Wide Grip)
AS54: Medium | AT54: EX078 — Single-Arm DB Row
AS55: Medium | AT55: EX043 — Single-Leg Balance Hold

Sheet Legend
A1: CONTROLLED VOCABULARY — LEGEND
A3: EXERCISE TYPES
A4: Type | B4: Category | C4: Definition
A5: Strength | B5: Primary | C5: Max force production under load — barbell, DB, KB, bodyweight
A6: Power | B6: Primary | C6: Rate of force development — explosive movements (Olympic lifts, loaded jumps)
A7: Plyometric | B7: Primary | C7: Bodyweight explosive — stretch-shortening cycle (jumps, bounds, hops)
A8: Isometric | B8: Primary | C8: Static hold under load or bodyweight — no joint movement
A9: Hypertrophy | B9: Primary | C9: Volume-based muscle building — moderate load, higher rep, shorter rest
A10: Activation / Primer | B10: Support | C10: Low-load neuromuscular pre-activation before primary training
A11: Balance / Proprioception | B11: Support | C11: Neuromuscular control on stable or unstable surface
A12: Agility | B12: Support | C12: Change of direction, footwork, reaction time
A13: Loaded Carry | B13: Primary | C13: Sustained postural integrity under load while moving
A14: Aerobic / Endurance | B14: Primary | C14: Sustained cardio — the sport modalities themselves
A15: Interval / Tempo | B15: Primary | C15: Structured intensity within an aerobic modality
... A21: Yoga / Pilates | B21: Support | C21: Integrated flexibility + isometric + balance + breathwork
A23: MOVEMENT PATTERNS
A24: Pattern | B24: Definition
A25: Squat | B25: Bilateral knee and hip flexion — vertical load
A26: Hinge | B26: Hip-dominant posterior chain — deadlift family
A27: Push-H | B27: Horizontal push — bench press, push-up family
A28: Push-V | B28: Vertical push — overhead press family
A29: Pull-H | B29: Horizontal pull — row family
A30: Pull-V | B30: Vertical pull — pull-up, lat pulldown family
A31: Carry | B31: Loaded locomotion — farmer carry, ruck family
A32: Rotation | B32: Rotational movement — twist, chop, swing family
A33: Anti-Rotation | B33: Resisting rotation — Pallof press, plank family
A34: Anti-Extension | B34: Resisting spinal extension — plank, dead bug family
A35: Anti-Flexion | B35: Resisting spinal flexion — suitcase carry, side plank family
... A43: Breathwork | B43: Deliberate respiratory pattern — box breathing, diaphragmatic
A45: PRIORITY (Sport-Exercise Map)
A46: Priority | B46: Definition
A47: Critical | B47: Core to sport performance — would meaningfully impair race result without it
A48: High | B48: Strong carryover — should be in regular training rotation
A49: Medium | B49: Useful but not essential — rotate in periodically
A50: Low | B50: Accessory — minor contribution or indirect benefit
A52: NOVELTY
A53: Tag | B53: Definition
A54: Common | B54: Well-known — widely used across mainstream training
A55: Specialized | B55: Sport-specific or niche — used in targeted training contexts
A57: Attribute
A58: Progression Exercise | B58: The next harder version within the same movement family — increase load, instability, or complexity
A59: Regression Exercise | B59: The easier version within the same movement family — reduce load, add stability, or use bilateral version
A60: Equipment Substitutes | B60: Alternative equipment or exercises when primary equipment unavailable — maintains similar training stimulus
A61: Contraindicated Body Parts | B61: Structured body part list extracted from Injury Flags — use for injury-based filtering
